[{"name":"11 Kilometerweg","postalCode":"37431","locality":"Harz (Landkreis Göttingen)","municipality":{"key":"03159501","name":"Harz (Landkreis Göttingen), gemfr. Geb.","type":"Gemeindefreies_Gebiet_Unbewohnt"},"district":{"key":"03159","name":"Göttingen","type":"Landkreis"},"federalState":{"key":"03","name":"Niedersachsen"}},{"name":"13.November-Weg","postalCode":"37520","locality":"Harz (Landkreis Göttingen)","municipality":{"key":"03159501","name":"Harz (Landkreis Göttingen), gemfr. Geb.","type":"Gemeindefreies_Gebiet_Unbewohnt"},"district":{"key":"03159","name":"Göttingen","type":"Landkreis"},"federalState":{"key":"03","name":"Niedersachsen"}},{"name":"1. Eckerhangweg","postalCode":"38667","locality":"Bad Harzburg","municipality":{"key":"03153002","name":"Bad Harzburg, Stadt","type":"Stadt"},"district":{"key":"03153","name":"Goslar","type":"Landkreis"},"federalState":{"key":"03","name":"Niedersachsen"}},{"name":"48-Pfennig-Weg","postalCode":"38667","locality":"Harz (LK Goslar)","municipality":{"key":"03153504","name":"Harz (Landkreis Goslar), gemfr. Gebiet","type":"Gemeindefreies_Gebiet_Unbewohnt"},"district":{"key":"03153","name":"Goslar","type":"Landkreis"},"federalState":{"key":"03","name":"Niedersachsen"}},{"name":"An der Schule","postalCode":"06458","locality":"Hedersleben","municipality":{"key":"15085160","name":"Hedersleben","type":"Kreisangehörige_Gemeinde"},"district":{"key":"15085","name":"Harz","type":"Landkreis"},"federalState":{"key":"15","name":"Sachsen-Anhalt"}},{"name":"Angermühle","postalCode":"06458","locality":"Hedersleben","municipality":{"key":"15085160","name":"Hedersleben","type":"Kreisangehörige_Gemeinde"},"district":{"key":"15085","name":"Harz","type":"Landkreis"},"federalState":{"key":"15","name":"Sachsen-Anhalt"}},{"name":"Angerstr.","postalCode":"06458","locality":"Hedersleben","municipality":{"key":"15085160","name":"Hedersleben","type":"Kreisangehörige_Gemeinde"},"district":{"key":"15085","name":"Harz","type":"Landkreis"},"federalState":{"key":"15","name":"Sachsen-Anhalt"}},{"name":"Breite Str.","postalCode":"06458","locality":"Hedersleben","municipality":{"key":"15085160","name":"Hedersleben","type":"Kreisangehörige_Gemeinde"},"district":{"key":"15085","name":"Harz","type":"Landkreis"},"federalState":{"key":"15","name":"Sachsen-Anhalt"}},{"name":"Carl-Georg-Koch-Ring","postalCode":"38667","locality":"Bad Harzburg","municipality":{"key":"03153002","name":"Bad Harzburg, Stadt","type":"Stadt"},"district":{"key":"03153","name":"Goslar","type":"Landkreis"},"federalState":{"key":"03","name":"Niedersachsen"}},{"name":"Carl-Goerdeler-Ring","postalCode":"38667","locality":"Bad Harzburg","municipality":{"key":"03153002","name":"Bad Harzburg, Stadt","type":"Stadt"},"district":{"key":"03153","name":"Goslar","type":"Landkreis"},"federalState":{"key":"03","name":"Niedersachsen"}},{"name":"Carl-Preen-Weg","postalCode":"38875","locality":"Oberharz am Brocken","municipality":{"key":"15085228","name":"Oberharz am Brocken, Stadt","type":"Stadt"},"district":{"key":"15085","name":"Harz","type":"Landkreis"},"federalState":{"key":"15","name":"Sachsen-Anhalt"}},{"name":"Castendyckstr.","postalCode":"38667","locality":"Bad Harzburg","municipality":{"key":"03153002","name":"Bad Harzburg, Stadt","type":"Stadt"},"district":{"key":"03153","name":"Goslar","type":"Landkreis"},"federalState":{"key":"03","name":"Niedersachsen"}},{"name":"Christian-Ludwig-Str.","postalCode":"37412","locality":"Herzberg am Harz","municipality":{"key":"03159019","name":"Herzberg am Harz, Stadt","type":"Stadt"},"district":{"key":"03159","name":"Göttingen","type":"Landkreis"},"federalState":{"key":"03","name":"Niedersachsen"}},{"name":"Clausbergweg","postalCode":"37520","locality":"Harz (Landkreis Göttingen)","municipality":{"key":"03159501","name":"Harz (Landkreis Göttingen), gemfr. Geb.","type":"Gemeindefreies_Gebiet_Unbewohnt"},"district":{"key":"03159","name":"Göttingen","type":"Landkreis"},"federalState":{"key":"03","name":"Niedersachsen"}},{"name":"Crausestr.","postalCode":"37412","locality":"Herzberg am Harz","municipality":{"key":"03159019","name":"Herzberg am Harz, Stadt","type":"Stadt"},"district":{"key":"03159","name":"Göttingen","type":"Landkreis"},"federalState":{"key":"03","name":"Niedersachsen"}},{"name":"Dachsweg","postalCode":"37431","locality":"Bad Lauterberg im Harz","municipality":{"key":"03159003","name":"Bad Lauterberg im Harz, Stadt","type":"Stadt"},"district":{"key":"03159","name":"Göttingen","type":"Landkreis"},"federalState":{"key":"03","name":"Niedersachsen"}},{"name":"Dachsweg","postalCode":"37520","locality":"Osterode am Harz","municipality":{"key":"03159026","name":"Osterode am Harz, Stadt","type":"Stadt"},"district":{"key":"03159","name":"Göttingen","type":"Landkreis"},"federalState":{"key":"03","name":"Niedersachsen"}},{"name":"Dachsweg","postalCode":"38667","locality":"Harz (LK Goslar)","municipality":{"key":"03153504","name":"Harz (Landkreis Goslar), gemfr. Gebiet","type":"Gemeindefreies_Gebiet_Unbewohnt"},"district":{"key":"03153","name":"Goslar","type":"Landkreis"},"federalState":{"key":"03","name":"Niedersachsen"}},{"name":"Dahlienstr.","postalCode":"37412","locality":"Herzberg am Harz","municipality":{"key":"03159019","name":"Herzberg am Harz, Stadt","type":"Stadt"},"district":{"key":"03159","name":"Göttingen","type":"Landkreis"},"federalState":{"key":"03","name":"Niedersachsen"}},{"name":"Dahlienstr.","postalCode":"37520","locality":"Osterode am Harz","municipality":{"key":"03159026","name":"Osterode am Harz, Stadt","type":"Stadt"},"district":{"key":"03159","name":"Göttingen","type":"Landkreis"},"federalState":{"key":"03","name":"Niedersachsen"}},{"name":"Dahlienweg","postalCode":"37197","locality":"Hattorf am Harz","municipality":{"key":"03159018","name":"Hattorf am Harz","type":"Kreisangehörige_Gemeinde"},"district":{"key":"03159","name":"Göttingen","type":"Landkreis"},"federalState":{"key":"03","name":"Niedersachsen"}},{"name":"Damaschkesiedlung","postalCode":"38855","locality":"Nordharz","municipality":{"key":"15085227","name":"Nordharz","type":"Kreisangehörige_Gemeinde"},"district":{"key":"15085","name":"Harz","type":"Landkreis"},"federalState":{"key":"15","name":"Sachsen-Anhalt"}},{"name":"Damm","postalCode":"06463","locality":"Falkenstein/Harz","municipality":{"key":"15085110","name":"Falkenstein/Harz, Stadt","type":"Stadt"},"district":{"key":"15085","name":"Harz","type":"Landkreis"},"federalState":{"key":"15","name":"Sachsen-Anhalt"}},{"name":"Dammbachtal","postalCode":"38877","locality":"Oberharz am Brocken","municipality":{"key":"15085228","name":"Oberharz am Brocken, Stadt","type":"Stadt"},"district":{"key":"15085","name":"Harz","type":"Landkreis"},"federalState":{"key":"15","name":"Sachsen-Anhalt"}},{"name":"Dammbachtal","postalCode":"38899","locality":"Oberharz am Brocken","municipality":{"key":"15085228","name":"Oberharz am Brocken, Stadt","type":"Stadt"},"district":{"key":"15085","name":"Harz","type":"Landkreis"},"federalState":{"key":"15","name":"Sachsen-Anhalt"}},{"name":"Dammweg","postalCode":"37412","locality":"Herzberg am Harz","municipality":{"key":"03159019","name":"Herzberg am Harz, Stadt","type":"Stadt"},"district":{"key":"03159","name":"Göttingen","type":"Landkreis"},"federalState":{"key":"03","name":"Niedersachsen"}},{"name":"Dammwiese","postalCode":"37431","locality":"Bad Lauterberg im Harz","municipality":{"key":"03159003","name":"Bad Lauterberg im Harz, Stadt","type":"Stadt"},"district":{"key":"03159","name":"Göttingen","type":"Landkreis"},"federalState":{"key":"03","name":"Niedersachsen"}},{"name":"Dammwiese","postalCode":"38667","locality":"Bad Harzburg","municipality":{"key":"03153002","name":"Bad Harzburg, Stadt","type":"Stadt"},"district":{"key":"03153","name":"Goslar","type":"Landkreis"},"federalState":{"key":"03","name":"Niedersachsen"}},{"name":"Dankeröder Str.","postalCode":"06493","locality":"Harzgerode","municipality":{"key":"15085145","name":"Harzgerode, Stadt","type":"Stadt"},"district":{"key":"15085","name":"Harz","type":"Landkreis"},"federalState":{"key":"15","name":"Sachsen-Anhalt"}},{"name":"Dankworthstr.","postalCode":"38667","locality":"Bad Harzburg","municipality":{"key":"03153002","name":"Bad Harzburg, Stadt","type":"Stadt"},"district":{"key":"03153","name":"Goslar","type":"Landkreis"},"federalState":{"key":"03","name":"Niedersachsen"}},{"name":"Danstedter Weg","postalCode":"38855","locality":"Nordharz","municipality":{"key":"15085227","name":"Nordharz","type":"Kreisangehörige_Gemeinde"},"district":{"key":"15085","name":"Harz","type":"Landkreis"},"federalState":{"key":"15","name":"Sachsen-Anhalt"}},{"name":"Danziger Str.","postalCode":"37197","locality":"Hattorf am Harz","municipality":{"key":"03159018","name":"Hattorf am Harz","type":"Kreisangehörige_Gemeinde"},"district":{"key":"03159","name":"Göttingen","type":"Landkreis"},"federalState":{"key":"03","name":"Niedersachsen"}},{"name":"Danziger Str.","postalCode":"37431","locality":"Bad Lauterberg im Harz","municipality":{"key":"03159003","name":"Bad Lauterberg im Harz, Stadt","type":"Stadt"},"district":{"key":"03159","name":"Göttingen","type":"Landkreis"},"federalState":{"key":"03","name":"Niedersachsen"}},{"name":"Danziger Str.","postalCode":"37520","locality":"Osterode am Harz","municipality":{"key":"03159026","name":"Osterode am Harz, Stadt","type":"Stadt"},"district":{"key":"03159","name":"Göttingen","type":"Landkreis"},"federalState":{"key":"03","name":"Niedersachsen"}},{"name":"Degenkopfweg","postalCode":"37520","locality":"Osterode am Harz","municipality":{"key":"03159026","name":"Osterode am Harz, Stadt","type":"Stadt"},"district":{"key":"03159","name":"Göttingen","type":"Landkreis"},"federalState":{"key":"03","name":"Niedersachsen"}},{"name":"Dehneplatz","postalCode":"38723","locality":"Harz (LK Goslar)","municipality":{"key":"03153504","name":"Harz (Landkreis Goslar), gemfr. Gebiet","type":"Gemeindefreies_Gebiet_Unbewohnt"},"district":{"key":"03153","name":"Goslar","type":"Landkreis"},"federalState":{"key":"03","name":"Niedersachsen"}},{"name":"Dehnestr.","postalCode":"38723","locality":"Harz (LK Goslar)","municipality":{"key":"03153504","name":"Harz (Landkreis Goslar), gemfr. Gebiet","type":"Gemeindefreies_Gebiet_Unbewohnt"},"district":{"key":"03153","name":"Goslar","type":"Landkreis"},"federalState":{"key":"03","name":"Niedersachsen"}},{"name":"Deilichstr.","postalCode":"38667","locality":"Bad Harzburg","municipality":{"key":"03153002","name":"Bad Harzburg, Stadt","type":"Stadt"},"district":{"key":"03153","name":"Goslar","type":"Landkreis"},"federalState":{"key":"03","name":"Niedersachsen"}},{"name":"Denkmalsplatz","postalCode":"38875","locality":"Oberharz am Brocken","municipality":{"key":"15085228","name":"Oberharz am Brocken, Stadt","type":"Stadt"},"district":{"key":"15085","name":"Harz","type":"Landkreis"},"federalState":{"key":"15","name":"Sachsen-Anhalt"}},{"name":"Denkmalsweg","postalCode":"37412","locality":"Herzberg am Harz","municipality":{"key":"03159019","name":"Herzberg am Harz, Stadt","type":"Stadt"},"district":{"key":"03159","name":"Göttingen","type":"Landkreis"},"federalState":{"key":"03","name":"Niedersachsen"}},{"name":"Derenburger Weg","postalCode":"38855","locality":"Nordharz","municipality":{"key":"15085227","name":"Nordharz","type":"Kreisangehörige_Gemeinde"},"district":{"key":"15085","name":"Harz","type":"Landkreis"},"federalState":{"key":"15","name":"Sachsen-Anhalt"}},{"name":"Dessauer Weg","postalCode":"06493","locality":"Harzgerode","municipality":{"key":"15085145","name":"Harzgerode, Stadt","type":"Stadt"},"district":{"key":"15085","name":"Harz","type":"Landkreis"},"federalState":{"key":"15","name":"Sachsen-Anhalt"}},{"name":"DETA-Str.","postalCode":"37431","locality":"Bad Lauterberg im Harz","municipality":{"key":"03159003","name":"Bad Lauterberg im Harz, Stadt","type":"Stadt"},"district":{"key":"03159","name":"Göttingen","type":"Landkreis"},"federalState":{"key":"03","name":"Niedersachsen"}},{"name":"Die Lange","postalCode":"38875","locality":"Oberharz am Brocken","municipality":{"key":"15085228","name":"Oberharz am Brocken, Stadt","type":"Stadt"},"district":{"key":"15085","name":"Harz","type":"Landkreis"},"federalState":{"key":"15","name":"Sachsen-Anhalt"}},{"name":"Die Lange","postalCode":"38889","locality":"Oberharz am Brocken","municipality":{"key":"15085228","name":"Oberharz am Brocken, Stadt","type":"Stadt"},"district":{"key":"15085","name":"Harz","type":"Landkreis"},"federalState":{"key":"15","name":"Sachsen-Anhalt"}},{"name":"Dielenplan","postalCode":"37520","locality":"Osterode am Harz","municipality":{"key":"03159026","name":"Osterode am Harz, Stadt","type":"Stadt"},"district":{"key":"03159","name":"Göttingen","type":"Landkreis"},"federalState":{"key":"03","name":"Niedersachsen"}},{"name":"Die Sechsundsechzig","postalCode":"37520","locality":"Osterode am Harz","municipality":{"key":"03159026","name":"Osterode am Harz, Stadt","type":"Stadt"},"district":{"key":"03159","name":"Göttingen","type":"Landkreis"},"federalState":{"key":"03","name":"Niedersachsen"}},{"name":"Dietrichsbergweg","postalCode":"38707","locality":"Harz (LK Goslar)","municipality":{"key":"03153504","name":"Harz (Landkreis Goslar), gemfr. Gebiet","type":"Gemeindefreies_Gebiet_Unbewohnt"},"district":{"key":"03153","name":"Goslar","type":"Landkreis"},"federalState":{"key":"03","name":"Niedersachsen"}},{"name":"Dietrichstal","postalCode":"37431","locality":"Bad Lauterberg im Harz","municipality":{"key":"03159003","name":"Bad Lauterberg im Harz, Stadt","type":"Stadt"},"district":{"key":"03159","name":"Göttingen","type":"Landkreis"},"federalState":{"key":"03","name":"Niedersachsen"}},{"name":"Distelgasse","postalCode":"06463","locality":"Falkenstein/Harz","municipality":{"key":"15085110","name":"Falkenstein/Harz, Stadt","type":"Stadt"},"district":{"key":"15085","name":"Harz","type":"Landkreis"},"federalState":{"key":"15","name":"Sachsen-Anhalt"}},{"name":"Distelweg","postalCode":"37520","locality":"Harz (Landkreis Göttingen)","municipality":{"key":"03159501","name":"Harz (Landkreis Göttingen), gemfr. Geb.","type":"Gemeindefreies_Gebiet_Unbewohnt"},"district":{"key":"03159","name":"Göttingen","type":"Landkreis"},"federalState":{"key":"03","name":"Niedersachsen"}},{"name":"Distelweg","postalCode":"37520","locality":"Osterode am Harz","municipality":{"key":"03159026","name":"Osterode am Harz, Stadt","type":"Stadt"},"district":{"key":"03159","name":"Göttingen","type":"Landkreis"},"federalState":{"key":"03","name":"Niedersachsen"}},{"name":"Dittichenröder Dorfstr.","postalCode":"06536","locality":"Südharz","municipality":{"key":"15087412","name":"Südharz","type":"Kreisangehörige_Gemeinde"},"district":{"key":"15087","name":"Mansfeld-Südharz","type":"Landkreis"},"federalState":{"key":"15","name":"Sachsen-Anhalt"}},{"name":"Doktorgasse","postalCode":"38855","locality":"Nordharz","municipality":{"key":"15085227","name":"Nordharz","type":"Kreisangehörige_Gemeinde"},"district":{"key":"15085","name":"Harz","type":"Landkreis"},"federalState":{"key":"15","name":"Sachsen-Anhalt"}},{"name":"Doktor-Hermannes-Weg","postalCode":"37412","locality":"Herzberg am Harz","municipality":{"key":"03159019","name":"Herzberg am Harz, Stadt","type":"Stadt"},"district":{"key":"03159","name":"Göttingen","type":"Landkreis"},"federalState":{"key":"03","name":"Niedersachsen"}},{"name":"Doktor-Jasper-Plan","postalCode":"38875","locality":"Oberharz am Brocken","municipality":{"key":"15085228","name":"Oberharz am Brocken, Stadt","type":"Stadt"},"district":{"key":"15085","name":"Harz","type":"Landkreis"},"federalState":{"key":"15","name":"Sachsen-Anhalt"}},{"name":"Dolomitstr.","postalCode":"37431","locality":"Bad Lauterberg im Harz","municipality":{"key":"03159003","name":"Bad Lauterberg im Harz, Stadt","type":"Stadt"},"district":{"key":"03159","name":"Göttingen","type":"Landkreis"},"federalState":{"key":"03","name":"Niedersachsen"}},{"name":"Domänenhof","postalCode":"06536","locality":"Südharz","municipality":{"key":"15087412","name":"Südharz","type":"Kreisangehörige_Gemeinde"},"district":{"key":"15087","name":"Mansfeld-Südharz","type":"Landkreis"},"federalState":{"key":"15","name":"Sachsen-Anhalt"}},{"name":"Domänenweg","postalCode":"37431","locality":"Bad Lauterberg im Harz","municipality":{"key":"03159003","name":"Bad Lauterberg im Harz, Stadt","type":"Stadt"},"district":{"key":"03159","name":"Göttingen","type":"Landkreis"},"federalState":{"key":"03","name":"Niedersachsen"}},{"name":"Domeyerpark","postalCode":"37412","locality":"Herzberg am Harz","municipality":{"key":"03159019","name":"Herzberg am Harz, Stadt","type":"Stadt"},"district":{"key":"03159","name":"Göttingen","type":"Landkreis"},"federalState":{"key":"03","name":"Niedersachsen"}},{"name":"Dommesstr.","postalCode":"38667","locality":"Bad Harzburg","municipality":{"key":"03153002","name":"Bad Harzburg, Stadt","type":"Stadt"},"district":{"key":"03153","name":"Goslar","type":"Landkreis"},"federalState":{"key":"03","name":"Niedersachsen"}},{"name":"Dorfplatz","postalCode":"99768","locality":"Harztor","municipality":{"key":"16062065","name":"Harztor","type":"Kreisangehörige_Gemeinde"},"district":{"key":"16062","name":"Nordhausen","type":"Landkreis"},"federalState":{"key":"16","name":"Thüringen"}},{"name":"Dorfstr.","postalCode":"06493","locality":"Harzgerode","municipality":{"key":"15085145","name":"Harzgerode, Stadt","type":"Stadt"},"district":{"key":"15085","name":"Harz","type":"Landkreis"},"federalState":{"key":"15","name":"Sachsen-Anhalt"}},{"name":"Dorfstr.","postalCode":"06536","locality":"Südharz","municipality":{"key":"15087412","name":"Südharz","type":"Kreisangehörige_Gemeinde"},"district":{"key":"15087","name":"Mansfeld-Südharz","type":"Landkreis"},"federalState":{"key":"15","name":"Sachsen-Anhalt"}},{"name":"Dorfstr.","postalCode":"06543","locality":"Falkenstein/Harz","municipality":{"key":"15085110","name":"Falkenstein/Harz, Stadt","type":"Stadt"},"district":{"key":"15085","name":"Harz","type":"Landkreis"},"federalState":{"key":"15","name":"Sachsen-Anhalt"}},{"name":"Ebersbachstr.","postalCode":"38875","locality":"Oberharz am Brocken","municipality":{"key":"15085228","name":"Oberharz am Brocken, Stadt","type":"Stadt"},"district":{"key":"15085","name":"Harz","type":"Landkreis"},"federalState":{"key":"15","name":"Sachsen-Anhalt"}},{"name":"Ebersberg Kammweg","postalCode":"38700","locality":"Harz (LK Goslar)","municipality":{"key":"03153504","name":"Harz (Landkreis Goslar), gemfr. Gebiet","type":"Gemeindefreies_Gebiet_Unbewohnt"},"district":{"key":"03153","name":"Goslar","type":"Landkreis"},"federalState":{"key":"03","name":"Niedersachsen"}},{"name":"Ebersbergstr.","postalCode":"38700","locality":"Harz (LK Goslar)","municipality":{"key":"03153504","name":"Harz (Landkreis Goslar), gemfr. Gebiet","type":"Gemeindefreies_Gebiet_Unbewohnt"},"district":{"key":"03153","name":"Goslar","type":"Landkreis"},"federalState":{"key":"03","name":"Niedersachsen"}},{"name":"Ebersburg-Rundweg","postalCode":"99768","locality":"Harztor","municipality":{"key":"16062065","name":"Harztor","type":"Kreisangehörige_Gemeinde"},"district":{"key":"16062","name":"Nordhausen","type":"Landkreis"},"federalState":{"key":"16","name":"Thüringen"}},{"name":"Eckertalstr.","postalCode":"38667","locality":"Bad Harzburg","municipality":{"key":"03153002","name":"Bad Harzburg, Stadt","type":"Stadt"},"district":{"key":"03153","name":"Goslar","type":"Landkreis"},"federalState":{"key":"03","name":"Niedersachsen"}},{"name":"Eckstr.","postalCode":"38667","locality":"Bad Harzburg","municipality":{"key":"03153002","name":"Bad Harzburg, Stadt","type":"Stadt"},"district":{"key":"03153","name":"Goslar","type":"Landkreis"},"federalState":{"key":"03","name":"Niedersachsen"}},{"name":"Edelweißstr.","postalCode":"37412","locality":"Herzberg am Harz","municipality":{"key":"03159019","name":"Herzberg am Harz, Stadt","type":"Stadt"},"district":{"key":"03159","name":"Göttingen","type":"Landkreis"},"federalState":{"key":"03","name":"Niedersachsen"}},{"name":"Edelweißstr.","postalCode":"37520","locality":"Osterode am Harz","municipality":{"key":"03159026","name":"Osterode am Harz, Stadt","type":"Stadt"},"district":{"key":"03159","name":"Göttingen","type":"Landkreis"},"federalState":{"key":"03","name":"Niedersachsen"}},{"name":"Eggeröder Brunnen","postalCode":"38875","locality":"Oberharz am Brocken","municipality":{"key":"15085228","name":"Oberharz am Brocken, Stadt","type":"Stadt"},"district":{"key":"15085","name":"Harz","type":"Landkreis"},"federalState":{"key":"15","name":"Sachsen-Anhalt"}},{"name":"Eichberg","postalCode":"99768","locality":"Harztor","municipality":{"key":"16062065","name":"Harztor","type":"Kreisangehörige_Gemeinde"},"district":{"key":"16062","name":"Nordhausen","type":"Landkreis"},"federalState":{"key":"16","name":"Thüringen"}},{"name":"Eichbergring","postalCode":"06493","locality":"Harzgerode","municipality":{"key":"15085145","name":"Harzgerode, Stadt","type":"Stadt"},"district":{"key":"15085","name":"Harz","type":"Landkreis"},"federalState":{"key":"15","name":"Sachsen-Anhalt"}},{"name":"Eichelbergstr.","postalCode":"37520","locality":"Harz (Landkreis Göttingen)","municipality":{"key":"03159501","name":"Harz (Landkreis Göttingen), gemfr. Geb.","type":"Gemeindefreies_Gebiet_Unbewohnt"},"district":{"key":"03159","name":"Göttingen","type":"Landkreis"},"federalState":{"key":"03","name":"Niedersachsen"}},{"name":"Eichelnkopfschneise","postalCode":"37431","locality":"Harz (Landkreis Göttingen)","municipality":{"key":"03159501","name":"Harz (Landkreis Göttingen), gemfr. Geb.","type":"Gemeindefreies_Gebiet_Unbewohnt"},"district":{"key":"03159","name":"Göttingen","type":"Landkreis"},"federalState":{"key":"03","name":"Niedersachsen"}},{"name":"Eichenberg","postalCode":"38877","locality":"Oberharz am Brocken","municipality":{"key":"15085228","name":"Oberharz am Brocken, Stadt","type":"Stadt"},"district":{"key":"15085","name":"Harz","type":"Landkreis"},"federalState":{"key":"15","name":"Sachsen-Anhalt"}},{"name":"Eichenbergrundweg","postalCode":"38667","locality":"Bad Harzburg","municipality":{"key":"03153002","name":"Bad Harzburg, Stadt","type":"Stadt"},"district":{"key":"03153","name":"Goslar","type":"Landkreis"},"federalState":{"key":"03","name":"Niedersachsen"}},{"name":"Eichenbergrundweg","postalCode":"38899","locality":"Oberharz am Brocken","municipality":{"key":"15085228","name":"Oberharz am Brocken, Stadt","type":"Stadt"},"district":{"key":"15085","name":"Harz","type":"Landkreis"},"federalState":{"key":"15","name":"Sachsen-Anhalt"}},{"name":"Eichenbergweg","postalCode":"38667","locality":"Bad Harzburg","municipality":{"key":"03153002","name":"Bad Harzburg, Stadt","type":"Stadt"},"district":{"key":"03153","name":"Goslar","type":"Landkreis"},"federalState":{"key":"03","name":"Niedersachsen"}},{"name":"Eichenbergweg","postalCode":"38667","locality":"Harz (LK Goslar)","municipality":{"key":"03153504","name":"Harz (Landkreis Goslar), gemfr. Gebiet","type":"Gemeindefreies_Gebiet_Unbewohnt"},"district":{"key":"03153","name":"Goslar","type":"Landkreis"},"federalState":{"key":"03","name":"Niedersachsen"}},{"name":"Eichenbornsweg","postalCode":"38667","locality":"Harz (LK Goslar)","municipality":{"key":"03153504","name":"Harz (Landkreis Goslar), gemfr. Gebiet","type":"Gemeindefreies_Gebiet_Unbewohnt"},"district":{"key":"03153","name":"Goslar","type":"Landkreis"},"federalState":{"key":"03","name":"Niedersachsen"}},{"name":"Eichendorffstr.","postalCode":"37431","locality":"Bad Lauterberg im Harz","municipality":{"key":"03159003","name":"Bad Lauterberg im Harz, Stadt","type":"Stadt"},"district":{"key":"03159","name":"Göttingen","type":"Landkreis"},"federalState":{"key":"03","name":"Niedersachsen"}},{"name":"Eichendorffstr.","postalCode":"38667","locality":"Bad Harzburg","municipality":{"key":"03153002","name":"Bad Harzburg, Stadt","type":"Stadt"},"district":{"key":"03153","name":"Goslar","type":"Landkreis"},"federalState":{"key":"03","name":"Niedersachsen"}},{"name":"Eichendorffweg","postalCode":"37197","locality":"Hattorf am Harz","municipality":{"key":"03159018","name":"Hattorf am Harz","type":"Kreisangehörige_Gemeinde"},"district":{"key":"03159","name":"Göttingen","type":"Landkreis"},"federalState":{"key":"03","name":"Niedersachsen"}},{"name":"Eichenforstallee","postalCode":"06536","locality":"Südharz","municipality":{"key":"15087412","name":"Südharz","type":"Kreisangehörige_Gemeinde"},"district":{"key":"15087","name":"Mansfeld-Südharz","type":"Landkreis"},"federalState":{"key":"15","name":"Sachsen-Anhalt"}},{"name":"Eichengrund","postalCode":"37520","locality":"Osterode am Harz","municipality":{"key":"03159026","name":"Osterode am Harz, Stadt","type":"Stadt"},"district":{"key":"03159","name":"Göttingen","type":"Landkreis"},"federalState":{"key":"03","name":"Niedersachsen"}},{"name":"Eichenleite","postalCode":"06536","locality":"Südharz","municipality":{"key":"15087412","name":"Südharz","type":"Kreisangehörige_Gemeinde"},"district":{"key":"15087","name":"Mansfeld-Südharz","type":"Landkreis"},"federalState":{"key":"15","name":"Sachsen-Anhalt"}},{"name":"Eichenweg","postalCode":"37520","locality":"Osterode am Harz","municipality":{"key":"03159026","name":"Osterode am Harz, Stadt","type":"Stadt"},"district":{"key":"03159","name":"Göttingen","type":"Landkreis"},"federalState":{"key":"03","name":"Niedersachsen"}},{"name":"Eichenweg","postalCode":"38667","locality":"Bad Harzburg","municipality":{"key":"03153002","name":"Bad Harzburg, Stadt","type":"Stadt"},"district":{"key":"03153","name":"Goslar","type":"Landkreis"},"federalState":{"key":"03","name":"Niedersachsen"}},{"name":"Eichenweg","postalCode":"38667","locality":"Harz (LK Goslar)","municipality":{"key":"03153504","name":"Harz (Landkreis Goslar), gemfr. Gebiet","type":"Gemeindefreies_Gebiet_Unbewohnt"},"district":{"key":"03153","name":"Goslar","type":"Landkreis"},"federalState":{"key":"03","name":"Niedersachsen"}},{"name":"Eichenweg","postalCode":"99768","locality":"Harztor","municipality":{"key":"16062065","name":"Harztor","type":"Kreisangehörige_Gemeinde"},"district":{"key":"16062","name":"Nordhausen","type":"Landkreis"},"federalState":{"key":"16","name":"Thüringen"}},{"name":"Eichlingshalber Weg","postalCode":"37520","locality":"Harz (Landkreis Göttingen)","municipality":{"key":"03159501","name":"Harz (Landkreis Göttingen), gemfr. Geb.","type":"Gemeindefreies_Gebiet_Unbewohnt"},"district":{"key":"03159","name":"Göttingen","type":"Landkreis"},"federalState":{"key":"03","name":"Niedersachsen"}},{"name":"Eickmuhlweg","postalCode":"38723","locality":"Harz (LK Goslar)","municipality":{"key":"03153504","name":"Harz (Landkreis Goslar), gemfr. Gebiet","type":"Gemeindefreies_Gebiet_Unbewohnt"},"district":{"key":"03153","name":"Goslar","type":"Landkreis"},"federalState":{"key":"03","name":"Niedersachsen"}},{"name":"Eierkornstalweg","postalCode":"37431","locality":"Harz (Landkreis Göttingen)","municipality":{"key":"03159501","name":"Harz (Landkreis Göttingen), gemfr. Geb.","type":"Gemeindefreies_Gebiet_Unbewohnt"},"district":{"key":"03159","name":"Göttingen","type":"Landkreis"},"federalState":{"key":"03","name":"Niedersachsen"}},{"name":"Einhornstr.","postalCode":"37412","locality":"Herzberg am Harz","municipality":{"key":"03159019","name":"Herzberg am Harz, Stadt","type":"Stadt"},"district":{"key":"03159","name":"Göttingen","type":"Landkreis"},"federalState":{"key":"03","name":"Niedersachsen"}},{"name":"Einhornweg","postalCode":"38899","locality":"Oberharz am Brocken","municipality":{"key":"15085228","name":"Oberharz am Brocken, Stadt","type":"Stadt"},"district":{"key":"15085","name":"Harz","type":"Landkreis"},"federalState":{"key":"15","name":"Sachsen-Anhalt"}},{"name":"Eisenacher Str.","postalCode":"37412","locality":"Herzberg am Harz","municipality":{"key":"03159019","name":"Herzberg am Harz, Stadt","type":"Stadt"},"district":{"key":"03159","name":"Göttingen","type":"Landkreis"},"federalState":{"key":"03","name":"Niedersachsen"}},{"name":"Eisener Stieg","postalCode":"37520","locality":"Harz (Landkreis Göttingen)","municipality":{"key":"03159501","name":"Harz (Landkreis Göttingen), gemfr. Geb.","type":"Gemeindefreies_Gebiet_Unbewohnt"},"district":{"key":"03159","name":"Göttingen","type":"Landkreis"},"federalState":{"key":"03","name":"Niedersachsen"}},{"name":"Eisenerzstr.","postalCode":"37431","locality":"Bad Lauterberg im Harz","municipality":{"key":"03159003","name":"Bad Lauterberg im Harz, Stadt","type":"Stadt"},"district":{"key":"03159","name":"Göttingen","type":"Landkreis"},"federalState":{"key":"03","name":"Niedersachsen"}},{"name":"Eisenhüttenweg","postalCode":"37520","locality":"Osterode am Harz","municipality":{"key":"03159026","name":"Osterode am Harz, Stadt","type":"Stadt"},"district":{"key":"03159","name":"Göttingen","type":"Landkreis"},"federalState":{"key":"03","name":"Niedersachsen"}},{"name":"Eisensteinbergweg","postalCode":"37444","locality":"Harz (LK Goslar)","municipality":{"key":"03153504","name":"Harz (Landkreis Goslar), gemfr. Gebiet","type":"Gemeindefreies_Gebiet_Unbewohnt"},"district":{"key":"03153","name":"Goslar","type":"Landkreis"},"federalState":{"key":"03","name":"Niedersachsen"}},{"name":"Eisensteinstr.","postalCode":"37520","locality":"Osterode am Harz","municipality":{"key":"03159026","name":"Osterode am Harz, Stadt","type":"Stadt"},"district":{"key":"03159","name":"Göttingen","type":"Landkreis"},"federalState":{"key":"03","name":"Niedersachsen"}},{"name":"Eisensteinstr.","postalCode":"38875","locality":"Oberharz am Brocken","municipality":{"key":"15085228","name":"Oberharz am Brocken, Stadt","type":"Stadt"},"district":{"key":"15085","name":"Harz","type":"Landkreis"},"federalState":{"key":"15","name":"Sachsen-Anhalt"}},{"name":"Eisensteinsweg","postalCode":"38723","locality":"Harz (LK Goslar)","municipality":{"key":"03153504","name":"Harz (Landkreis Goslar), gemfr. Gebiet","type":"Gemeindefreies_Gebiet_Unbewohnt"},"district":{"key":"03153","name":"Goslar","type":"Landkreis"},"federalState":{"key":"03","name":"Niedersachsen"}},{"name":"Eiserner Weg","postalCode":"38667","locality":"Harz (LK Goslar)","municipality":{"key":"03153504","name":"Harz (Landkreis Goslar), gemfr. Gebiet","type":"Gemeindefreies_Gebiet_Unbewohnt"},"district":{"key":"03153","name":"Goslar","type":"Landkreis"},"federalState":{"key":"03","name":"Niedersachsen"}},{"name":"Eisfeldsiedlung","postalCode":"06493","locality":"Harzgerode","municipality":{"key":"15085145","name":"Harzgerode, Stadt","type":"Stadt"},"district":{"key":"15085","name":"Harz","type":"Landkreis"},"federalState":{"key":"15","name":"Sachsen-Anhalt"}},{"name":"Elbinger Weg","postalCode":"37431","locality":"Bad Lauterberg im Harz","municipality":{"key":"03159003","name":"Bad Lauterberg im Harz, Stadt","type":"Stadt"},"district":{"key":"03159","name":"Göttingen","type":"Landkreis"},"federalState":{"key":"03","name":"Niedersachsen"}},{"name":"Elefantenweg","postalCode":"37520","locality":"Harz (Landkreis Göttingen)","municipality":{"key":"03159501","name":"Harz (Landkreis Göttingen), gemfr. Geb.","type":"Gemeindefreies_Gebiet_Unbewohnt"},"district":{"key":"03159","name":"Göttingen","type":"Landkreis"},"federalState":{"key":"03","name":"Niedersachsen"}},{"name":"Elendstal","postalCode":"38875","locality":"Oberharz am Brocken","municipality":{"key":"15085228","name":"Oberharz am Brocken, Stadt","type":"Stadt"},"district":{"key":"15085","name":"Harz","type":"Landkreis"},"federalState":{"key":"15","name":"Sachsen-Anhalt"}},{"name":"Eleonorenweg","postalCode":"37520","locality":"Harz (Landkreis Göttingen)","municipality":{"key":"03159501","name":"Harz (Landkreis Göttingen), gemfr. Geb.","type":"Gemeindefreies_Gebiet_Unbewohnt"},"district":{"key":"03159","name":"Göttingen","type":"Landkreis"},"federalState":{"key":"03","name":"Niedersachsen"}},{"name":"Elfensteinweg","postalCode":"38667","locality":"Harz (LK Goslar)","municipality":{"key":"03153504","name":"Harz (Landkreis Goslar), gemfr. Gebiet","type":"Gemeindefreies_Gebiet_Unbewohnt"},"district":{"key":"03153","name":"Goslar","type":"Landkreis"},"federalState":{"key":"03","name":"Niedersachsen"}},{"name":"Elfenstieg","postalCode":"38667","locality":"Bad Harzburg","municipality":{"key":"03153002","name":"Bad Harzburg, Stadt","type":"Stadt"},"district":{"key":"03153","name":"Goslar","type":"Landkreis"},"federalState":{"key":"03","name":"Niedersachsen"}},{"name":"Feldstr.","postalCode":"06458","locality":"Hedersleben","municipality":{"key":"15085160","name":"Hedersleben","type":"Kreisangehörige_Gemeinde"},"district":{"key":"15085","name":"Harz","type":"Landkreis"},"federalState":{"key":"15","name":"Sachsen-Anhalt"}},{"name":"Friedensstr.","postalCode":"06458","locality":"Hedersleben","municipality":{"key":"15085160","name":"Hedersleben","type":"Kreisangehörige_Gemeinde"},"district":{"key":"15085","name":"Harz","type":"Landkreis"},"federalState":{"key":"15","name":"Sachsen-Anhalt"}},{"name":"Gartenstr.","postalCode":"06458","locality":"Hedersleben","municipality":{"key":"15085160","name":"Hedersleben","type":"Kreisangehörige_Gemeinde"},"district":{"key":"15085","name":"Harz","type":"Landkreis"},"federalState":{"key":"15","name":"Sachsen-Anhalt"}},{"name":"Hakelstr.","postalCode":"06458","locality":"Hedersleben","municipality":{"key":"15085160","name":"Hedersleben","type":"Kreisangehörige_Gemeinde"},"district":{"key":"15085","name":"Harz","type":"Landkreis"},"federalState":{"key":"15","name":"Sachsen-Anhalt"}},{"name":"Halberstädter Str.","postalCode":"06458","locality":"Hedersleben","municipality":{"key":"15085160","name":"Hedersleben","type":"Kreisangehörige_Gemeinde"},"district":{"key":"15085","name":"Harz","type":"Landkreis"},"federalState":{"key":"15","name":"Sachsen-Anhalt"}},{"name":"Hausneindorfer Str.","postalCode":"06458","locality":"Hedersleben","municipality":{"key":"15085160","name":"Hedersleben","type":"Kreisangehörige_Gemeinde"},"district":{"key":"15085","name":"Harz","type":"Landkreis"},"federalState":{"key":"15","name":"Sachsen-Anhalt"}},{"name":"Hederslebener Weg","postalCode":"06458","locality":"Hedersleben","municipality":{"key":"15085160","name":"Hedersleben","type":"Kreisangehörige_Gemeinde"},"district":{"key":"15085","name":"Harz","type":"Landkreis"},"federalState":{"key":"15","name":"Sachsen-Anhalt"}},{"name":"Hüttenstr.","postalCode":"06458","locality":"Hedersleben","municipality":{"key":"15085160","name":"Hedersleben","type":"Kreisangehörige_Gemeinde"},"district":{"key":"15085","name":"Harz","type":"Landkreis"},"federalState":{"key":"15","name":"Sachsen-Anhalt"}},{"name":"Im Winkel","postalCode":"06458","locality":"Hedersleben","municipality":{"key":"15085160","name":"Hedersleben","type":"Kreisangehörige_Gemeinde"},"district":{"key":"15085","name":"Harz","type":"Landkreis"},"federalState":{"key":"15","name":"Sachsen-Anhalt"}},{"name":"Jordanstr.","postalCode":"06458","locality":"Hedersleben","municipality":{"key":"15085160","name":"Hedersleben","type":"Kreisangehörige_Gemeinde"},"district":{"key":"15085","name":"Harz","type":"Landkreis"},"federalState":{"key":"15","name":"Sachsen-Anhalt"}},{"name":"Klosterstr.","postalCode":"06458","locality":"Hedersleben","municipality":{"key":"15085160","name":"Hedersleben","type":"Kreisangehörige_Gemeinde"},"district":{"key":"15085","name":"Harz","type":"Landkreis"},"federalState":{"key":"15","name":"Sachsen-Anhalt"}},{"name":"Krumme Str.","postalCode":"06458","locality":"Hedersleben","municipality":{"key":"15085160","name":"Hedersleben","type":"Kreisangehörige_Gemeinde"},"district":{"key":"15085","name":"Harz","type":"Landkreis"},"federalState":{"key":"15","name":"Sachsen-Anhalt"}},{"name":"Lindenstr.","postalCode":"06458","locality":"Hedersleben","municipality":{"key":"15085160","name":"Hedersleben","type":"Kreisangehörige_Gemeinde"},"district":{"key":"15085","name":"Harz","type":"Landkreis"},"federalState":{"key":"15","name":"Sachsen-Anhalt"}},{"name":"Magdeburger Str.","postalCode":"06458","locality":"Hedersleben","municipality":{"key":"15085160","name":"Hedersleben","type":"Kreisangehörige_Gemeinde"},"district":{"key":"15085","name":"Harz","type":"Landkreis"},"federalState":{"key":"15","name":"Sachsen-Anhalt"}},{"name":"Markbergstr.","postalCode":"06458","locality":"Hedersleben","municipality":{"key":"15085160","name":"Hedersleben","type":"Kreisangehörige_Gemeinde"},"district":{"key":"15085","name":"Harz","type":"Landkreis"},"federalState":{"key":"15","name":"Sachsen-Anhalt"}},{"name":"Morgenstr.","postalCode":"06458","locality":"Hedersleben","municipality":{"key":"15085160","name":"Hedersleben","type":"Kreisangehörige_Gemeinde"},"district":{"key":"15085","name":"Harz","type":"Landkreis"},"federalState":{"key":"15","name":"Sachsen-Anhalt"}},{"name":"Mühlenstr.","postalCode":"06458","locality":"Hedersleben","municipality":{"key":"15085160","name":"Hedersleben","type":"Kreisangehörige_Gemeinde"},"district":{"key":"15085","name":"Harz","type":"Landkreis"},"federalState":{"key":"15","name":"Sachsen-Anhalt"}},{"name":"Nachthufe","postalCode":"38871","locality":"Nordharz","municipality":{"key":"15085227","name":"Nordharz","type":"Kreisangehörige_Gemeinde"},"district":{"key":"15085","name":"Harz","type":"Landkreis"},"federalState":{"key":"15","name":"Sachsen-Anhalt"}},{"name":"Nachtwächterweg","postalCode":"06536","locality":"Südharz","municipality":{"key":"15087412","name":"Südharz","type":"Kreisangehörige_Gemeinde"},"district":{"key":"15087","name":"Mansfeld-Südharz","type":"Landkreis"},"federalState":{"key":"15","name":"Sachsen-Anhalt"}},{"name":"Nasser Weg","postalCode":"37520","locality":"Harz (Landkreis Göttingen)","municipality":{"key":"03159501","name":"Harz (Landkreis Göttingen), gemfr. Geb.","type":"Gemeindefreies_Gebiet_Unbewohnt"},"district":{"key":"03159","name":"Göttingen","type":"Landkreis"},"federalState":{"key":"03","name":"Niedersachsen"}},{"name":"Nassestr.","postalCode":"06536","locality":"Südharz","municipality":{"key":"15087412","name":"Südharz","type":"Kreisangehörige_Gemeinde"},"district":{"key":"15087","name":"Mansfeld-Südharz","type":"Landkreis"},"federalState":{"key":"15","name":"Sachsen-Anhalt"}},{"name":"Nasse Str.","postalCode":"06536","locality":"Südharz","municipality":{"key":"15087412","name":"Südharz","type":"Kreisangehörige_Gemeinde"},"district":{"key":"15087","name":"Mansfeld-Südharz","type":"Landkreis"},"federalState":{"key":"15","name":"Sachsen-Anhalt"}},{"name":"Naturlehrpfad","postalCode":"06493","locality":"Harzgerode","municipality":{"key":"15085145","name":"Harzgerode, Stadt","type":"Stadt"},"district":{"key":"15085","name":"Harz","type":"Landkreis"},"federalState":{"key":"15","name":"Sachsen-Anhalt"}},{"name":"Naturlehrpfad","postalCode":"38899","locality":"Oberharz am Brocken","municipality":{"key":"15085228","name":"Oberharz am Brocken, Stadt","type":"Stadt"},"district":{"key":"15085","name":"Harz","type":"Landkreis"},"federalState":{"key":"15","name":"Sachsen-Anhalt"}},{"name":"Naturlehrpfad / Loipe","postalCode":"38899","locality":"Oberharz am Brocken","municipality":{"key":"15085228","name":"Oberharz am Brocken, Stadt","type":"Stadt"},"district":{"key":"15085","name":"Harz","type":"Landkreis"},"federalState":{"key":"15","name":"Sachsen-Anhalt"}},{"name":"Naturpfad","postalCode":"38685","locality":"Harz (LK Goslar)","municipality":{"key":"03153504","name":"Harz (Landkreis Goslar), gemfr. Gebiet","type":"Gemeindefreies_Gebiet_Unbewohnt"},"district":{"key":"03153","name":"Goslar","type":"Landkreis"},"federalState":{"key":"03","name":"Niedersachsen"}},{"name":"Neanderplatz","postalCode":"99768","locality":"Harztor","municipality":{"key":"16062065","name":"Harztor","type":"Kreisangehörige_Gemeinde"},"district":{"key":"16062","name":"Nordhausen","type":"Landkreis"},"federalState":{"key":"16","name":"Thüringen"}},{"name":"Neilespringweg","postalCode":"38723","locality":"Harz (LK Goslar)","municipality":{"key":"03153504","name":"Harz (Landkreis Goslar), gemfr. Gebiet","type":"Gemeindefreies_Gebiet_Unbewohnt"},"district":{"key":"03153","name":"Goslar","type":"Landkreis"},"federalState":{"key":"03","name":"Niedersachsen"}},{"name":"Neilestr.","postalCode":"38723","locality":"Harz (LK Goslar)","municipality":{"key":"03153504","name":"Harz (Landkreis Goslar), gemfr. Gebiet","type":"Gemeindefreies_Gebiet_Unbewohnt"},"district":{"key":"03153","name":"Goslar","type":"Landkreis"},"federalState":{"key":"03","name":"Niedersachsen"}},{"name":"Nelkenstr.","postalCode":"37412","locality":"Herzberg am Harz","municipality":{"key":"03159019","name":"Herzberg am Harz, Stadt","type":"Stadt"},"district":{"key":"03159","name":"Göttingen","type":"Landkreis"},"federalState":{"key":"03","name":"Niedersachsen"}},{"name":"Nelkenstr.","postalCode":"37412","locality":"Hörden am Harz","municipality":{"key":"03159020","name":"Hörden am Harz","type":"Kreisangehörige_Gemeinde"},"district":{"key":"03159","name":"Göttingen","type":"Landkreis"},"federalState":{"key":"03","name":"Niedersachsen"}},{"name":"Nelkenweg","postalCode":"37431","locality":"Bad Lauterberg im Harz","municipality":{"key":"03159003","name":"Bad Lauterberg im Harz, Stadt","type":"Stadt"},"district":{"key":"03159","name":"Göttingen","type":"Landkreis"},"federalState":{"key":"03","name":"Niedersachsen"}},{"name":"Nesselberg","postalCode":"99897","locality":"Tambach-Dietharz","municipality":{"key":"16067065","name":"Tambach-Dietharz/Thür. Wald, Stadt","type":"Stadt"},"district":{"key":"16067","name":"Gotha","type":"Landkreis"},"federalState":{"key":"16","name":"Thüringen"}},{"name":"Nesselweg","postalCode":"37431","locality":"Harz (Landkreis Göttingen)","municipality":{"key":"03159501","name":"Harz (Landkreis Göttingen), gemfr. Geb.","type":"Gemeindefreies_Gebiet_Unbewohnt"},"district":{"key":"03159","name":"Göttingen","type":"Landkreis"},"federalState":{"key":"03","name":"Niedersachsen"}},{"name":"Netzkater","postalCode":"99768","locality":"Harztor","municipality":{"key":"16062065","name":"Harztor","type":"Kreisangehörige_Gemeinde"},"district":{"key":"16062","name":"Nordhausen","type":"Landkreis"},"federalState":{"key":"16","name":"Thüringen"}},{"name":"Neudorfer Fußweg","postalCode":"06493","locality":"Harzgerode","municipality":{"key":"15085145","name":"Harzgerode, Stadt","type":"Stadt"},"district":{"key":"15085","name":"Harz","type":"Landkreis"},"federalState":{"key":"15","name":"Sachsen-Anhalt"}},{"name":"Neudorfer Weg","postalCode":"06493","locality":"Harzgerode","municipality":{"key":"15085145","name":"Harzgerode, Stadt","type":"Stadt"},"district":{"key":"15085","name":"Harz","type":"Landkreis"},"federalState":{"key":"15","name":"Sachsen-Anhalt"}},{"name":"Neue Bauernstr.","postalCode":"06463","locality":"Falkenstein/Harz","municipality":{"key":"15085110","name":"Falkenstein/Harz, Stadt","type":"Stadt"},"district":{"key":"15085","name":"Harz","type":"Landkreis"},"federalState":{"key":"15","name":"Sachsen-Anhalt"}},{"name":"Neue Erikabrücke","postalCode":"37431","locality":"Bad Lauterberg im Harz","municipality":{"key":"03159003","name":"Bad Lauterberg im Harz, Stadt","type":"Stadt"},"district":{"key":"03159","name":"Göttingen","type":"Landkreis"},"federalState":{"key":"03","name":"Niedersachsen"}},{"name":"Neue Forsthäuser","postalCode":"06493","locality":"Harzgerode","municipality":{"key":"15085145","name":"Harzgerode, Stadt","type":"Stadt"},"district":{"key":"15085","name":"Harz","type":"Landkreis"},"federalState":{"key":"15","name":"Sachsen-Anhalt"}},{"name":"Neue Hütte","postalCode":"38875","locality":"Oberharz am Brocken","municipality":{"key":"15085228","name":"Oberharz am Brocken, Stadt","type":"Stadt"},"district":{"key":"15085","name":"Harz","type":"Landkreis"},"federalState":{"key":"15","name":"Sachsen-Anhalt"}},{"name":"Neue Marktstr.","postalCode":"99768","locality":"Harztor","municipality":{"key":"16062065","name":"Harztor","type":"Kreisangehörige_Gemeinde"},"district":{"key":"16062","name":"Nordhausen","type":"Landkreis"},"federalState":{"key":"16","name":"Thüringen"}},{"name":"Neue Meinigstr.","postalCode":"38667","locality":"Bad Harzburg","municipality":{"key":"03153002","name":"Bad Harzburg, Stadt","type":"Stadt"},"district":{"key":"03153","name":"Goslar","type":"Landkreis"},"federalState":{"key":"03","name":"Niedersachsen"}},{"name":"Neuendorf","postalCode":"06536","locality":"Südharz","municipality":{"key":"15087412","name":"Südharz","type":"Kreisangehörige_Gemeinde"},"district":{"key":"15087","name":"Mansfeld-Südharz","type":"Landkreis"},"federalState":{"key":"15","name":"Sachsen-Anhalt"}},{"name":"Neuenfelder Weg","postalCode":"38871","locality":"Nordharz","municipality":{"key":"15085227","name":"Nordharz","type":"Kreisangehörige_Gemeinde"},"district":{"key":"15085","name":"Harz","type":"Landkreis"},"federalState":{"key":"15","name":"Sachsen-Anhalt"}},{"name":"Neue Reihe","postalCode":"06333","locality":"Falkenstein/Harz","municipality":{"key":"15085110","name":"Falkenstein/Harz, Stadt","type":"Stadt"},"district":{"key":"15085","name":"Harz","type":"Landkreis"},"federalState":{"key":"15","name":"Sachsen-Anhalt"}},{"name":"Neue Reihe","postalCode":"37520","locality":"Osterode am Harz","municipality":{"key":"03159026","name":"Osterode am Harz, Stadt","type":"Stadt"},"district":{"key":"03159","name":"Göttingen","type":"Landkreis"},"federalState":{"key":"03","name":"Niedersachsen"}},{"name":"Neuer Teichdamm","postalCode":"06536","locality":"Südharz","municipality":{"key":"15087412","name":"Südharz","type":"Kreisangehörige_Gemeinde"},"district":{"key":"15087","name":"Mansfeld-Südharz","type":"Landkreis"},"federalState":{"key":"15","name":"Sachsen-Anhalt"}},{"name":"Neuer Weg","postalCode":"06493","locality":"Harzgerode","municipality":{"key":"15085145","name":"Harzgerode, Stadt","type":"Stadt"},"district":{"key":"15085","name":"Harz","type":"Landkreis"},"federalState":{"key":"15","name":"Sachsen-Anhalt"}},{"name":"Neuer Weg","postalCode":"06543","locality":"Falkenstein/Harz","municipality":{"key":"15085110","name":"Falkenstein/Harz, Stadt","type":"Stadt"},"district":{"key":"15085","name":"Harz","type":"Landkreis"},"federalState":{"key":"15","name":"Sachsen-Anhalt"}},{"name":"Neuer Weg","postalCode":"37197","locality":"Hattorf am Harz","municipality":{"key":"03159018","name":"Hattorf am Harz","type":"Kreisangehörige_Gemeinde"},"district":{"key":"03159","name":"Göttingen","type":"Landkreis"},"federalState":{"key":"03","name":"Niedersachsen"}},{"name":"Neuer Weg","postalCode":"38667","locality":"Bad Harzburg","municipality":{"key":"03153002","name":"Bad Harzburg, Stadt","type":"Stadt"},"district":{"key":"03153","name":"Goslar","type":"Landkreis"},"federalState":{"key":"03","name":"Niedersachsen"}},{"name":"Neue Siedlung","postalCode":"06493","locality":"Harzgerode","municipality":{"key":"15085145","name":"Harzgerode, Stadt","type":"Stadt"},"district":{"key":"15085","name":"Harz","type":"Landkreis"},"federalState":{"key":"15","name":"Sachsen-Anhalt"}},{"name":"Neues Tor","postalCode":"06493","locality":"Harzgerode","municipality":{"key":"15085145","name":"Harzgerode, Stadt","type":"Stadt"},"district":{"key":"15085","name":"Harz","type":"Landkreis"},"federalState":{"key":"15","name":"Sachsen-Anhalt"}},{"name":"Neue Str.","postalCode":"06463","locality":"Falkenstein/Harz","municipality":{"key":"15085110","name":"Falkenstein/Harz, Stadt","type":"Stadt"},"district":{"key":"15085","name":"Harz","type":"Landkreis"},"federalState":{"key":"15","name":"Sachsen-Anhalt"}},{"name":"Neue Str.","postalCode":"06493","locality":"Harzgerode","municipality":{"key":"15085145","name":"Harzgerode, Stadt","type":"Stadt"},"district":{"key":"15085","name":"Harz","type":"Landkreis"},"federalState":{"key":"15","name":"Sachsen-Anhalt"}},{"name":"Neue Str.","postalCode":"06536","locality":"Südharz","municipality":{"key":"15087412","name":"Südharz","type":"Kreisangehörige_Gemeinde"},"district":{"key":"15087","name":"Mansfeld-Südharz","type":"Landkreis"},"federalState":{"key":"15","name":"Sachsen-Anhalt"}},{"name":"Neue Str.","postalCode":"38875","locality":"Oberharz am Brocken","municipality":{"key":"15085228","name":"Oberharz am Brocken, Stadt","type":"Stadt"},"district":{"key":"15085","name":"Harz","type":"Landkreis"},"federalState":{"key":"15","name":"Sachsen-Anhalt"}},{"name":"Neue Str.","postalCode":"38899","locality":"Oberharz am Brocken","municipality":{"key":"15085228","name":"Oberharz am Brocken, Stadt","type":"Stadt"},"district":{"key":"15085","name":"Harz","type":"Landkreis"},"federalState":{"key":"15","name":"Sachsen-Anhalt"}},{"name":"Neue Str.","postalCode":"99897","locality":"Tambach-Dietharz","municipality":{"key":"16067065","name":"Tambach-Dietharz/Thür. Wald, Stadt","type":"Stadt"},"district":{"key":"16067","name":"Gotha","type":"Landkreis"},"federalState":{"key":"16","name":"Thüringen"}},{"name":"Neue Welt","postalCode":"37199","locality":"Wulften am Harz","municipality":{"key":"03159039","name":"Wulften am Harz","type":"Kreisangehörige_Gemeinde"},"district":{"key":"03159","name":"Göttingen","type":"Landkreis"},"federalState":{"key":"03","name":"Niedersachsen"}},{"name":"Neustadt","postalCode":"06463","locality":"Falkenstein/Harz","municipality":{"key":"15085110","name":"Falkenstein/Harz, Stadt","type":"Stadt"},"district":{"key":"15085","name":"Harz","type":"Landkreis"},"federalState":{"key":"15","name":"Sachsen-Anhalt"}},{"name":"Neustadt","postalCode":"06493","locality":"Harzgerode","municipality":{"key":"15085145","name":"Harzgerode, Stadt","type":"Stadt"},"district":{"key":"15085","name":"Harz","type":"Landkreis"},"federalState":{"key":"15","name":"Sachsen-Anhalt"}},{"name":"Neustadt","postalCode":"06536","locality":"Südharz","municipality":{"key":"15087412","name":"Südharz","type":"Kreisangehörige_Gemeinde"},"district":{"key":"15087","name":"Mansfeld-Südharz","type":"Landkreis"},"federalState":{"key":"15","name":"Sachsen-Anhalt"}},{"name":"Neustadt","postalCode":"38871","locality":"Nordharz","municipality":{"key":"15085227","name":"Nordharz","type":"Kreisangehörige_Gemeinde"},"district":{"key":"15085","name":"Harz","type":"Landkreis"},"federalState":{"key":"15","name":"Sachsen-Anhalt"}},{"name":"Nickolsgasse","postalCode":"06493","locality":"Harzgerode","municipality":{"key":"15085145","name":"Harzgerode, Stadt","type":"Stadt"},"district":{"key":"15085","name":"Harz","type":"Landkreis"},"federalState":{"key":"15","name":"Sachsen-Anhalt"}},{"name":"Nicolairing","postalCode":"38667","locality":"Bad Harzburg","municipality":{"key":"03153002","name":"Bad Harzburg, Stadt","type":"Stadt"},"district":{"key":"03153","name":"Goslar","type":"Landkreis"},"federalState":{"key":"03","name":"Niedersachsen"}},{"name":"Oberbruch","postalCode":"38877","locality":"Oberharz am Brocken","municipality":{"key":"15085228","name":"Oberharz am Brocken, Stadt","type":"Stadt"},"district":{"key":"15085","name":"Harz","type":"Landkreis"},"federalState":{"key":"15","name":"Sachsen-Anhalt"}},{"name":"Oberdorf","postalCode":"06463","locality":"Falkenstein/Harz","municipality":{"key":"15085110","name":"Falkenstein/Harz, Stadt","type":"Stadt"},"district":{"key":"15085","name":"Harz","type":"Landkreis"},"federalState":{"key":"15","name":"Sachsen-Anhalt"}},{"name":"Oberdorf","postalCode":"06493","locality":"Harzgerode","municipality":{"key":"15085145","name":"Harzgerode, Stadt","type":"Stadt"},"district":{"key":"15085","name":"Harz","type":"Landkreis"},"federalState":{"key":"15","name":"Sachsen-Anhalt"}},{"name":"Oberdorf","postalCode":"37520","locality":"Osterode am Harz","municipality":{"key":"03159026","name":"Osterode am Harz, Stadt","type":"Stadt"},"district":{"key":"03159","name":"Göttingen","type":"Landkreis"},"federalState":{"key":"03","name":"Niedersachsen"}},{"name":"Oberdorf","postalCode":"38889","locality":"Oberharz am Brocken","municipality":{"key":"15085228","name":"Oberharz am Brocken, Stadt","type":"Stadt"},"district":{"key":"15085","name":"Harz","type":"Landkreis"},"federalState":{"key":"15","name":"Sachsen-Anhalt"}},{"name":"Oberdorfstr.","postalCode":"06536","locality":"Südharz","municipality":{"key":"15087412","name":"Südharz","type":"Kreisangehörige_Gemeinde"},"district":{"key":"15087","name":"Mansfeld-Südharz","type":"Landkreis"},"federalState":{"key":"15","name":"Sachsen-Anhalt"}},{"name":"Oberdorfstr.","postalCode":"37520","locality":"Osterode am Harz","municipality":{"key":"03159026","name":"Osterode am Harz, Stadt","type":"Stadt"},"district":{"key":"03159","name":"Göttingen","type":"Landkreis"},"federalState":{"key":"03","name":"Niedersachsen"}},{"name":"Oberdorfstr.","postalCode":"38871","locality":"Nordharz","municipality":{"key":"15085227","name":"Nordharz","type":"Kreisangehörige_Gemeinde"},"district":{"key":"15085","name":"Harz","type":"Landkreis"},"federalState":{"key":"15","name":"Sachsen-Anhalt"}},{"name":"Obere Freiheit","postalCode":"06493","locality":"Harzgerode","municipality":{"key":"15085145","name":"Harzgerode, Stadt","type":"Stadt"},"district":{"key":"15085","name":"Harz","type":"Landkreis"},"federalState":{"key":"15","name":"Sachsen-Anhalt"}},{"name":"Obere Gasse","postalCode":"06536","locality":"Südharz","municipality":{"key":"15087412","name":"Südharz","type":"Kreisangehörige_Gemeinde"},"district":{"key":"15087","name":"Mansfeld-Südharz","type":"Landkreis"},"federalState":{"key":"15","name":"Sachsen-Anhalt"}},{"name":"Obere Gasse","postalCode":"06543","locality":"Falkenstein/Harz","municipality":{"key":"15085110","name":"Falkenstein/Harz, Stadt","type":"Stadt"},"district":{"key":"15085","name":"Harz","type":"Landkreis"},"federalState":{"key":"15","name":"Sachsen-Anhalt"}},{"name":"Obere Harzstr.","postalCode":"37520","locality":"Osterode am Harz","municipality":{"key":"03159026","name":"Osterode am Harz, Stadt","type":"Stadt"},"district":{"key":"03159","name":"Göttingen","type":"Landkreis"},"federalState":{"key":"03","name":"Niedersachsen"}},{"name":"Obere Hauptstr.","postalCode":"06333","locality":"Falkenstein/Harz","municipality":{"key":"15085110","name":"Falkenstein/Harz, Stadt","type":"Stadt"},"district":{"key":"15085","name":"Harz","type":"Landkreis"},"federalState":{"key":"15","name":"Sachsen-Anhalt"}},{"name":"Obere Herrentalstr.","postalCode":"37520","locality":"Osterode am Harz","municipality":{"key":"03159026","name":"Osterode am Harz, Stadt","type":"Stadt"},"district":{"key":"03159","name":"Göttingen","type":"Landkreis"},"federalState":{"key":"03","name":"Niedersachsen"}},{"name":"Obere Hofbreite","postalCode":"38667","locality":"Bad Harzburg","municipality":{"key":"03153002","name":"Bad Harzburg, Stadt","type":"Stadt"},"district":{"key":"03153","name":"Goslar","type":"Landkreis"},"federalState":{"key":"03","name":"Niedersachsen"}},{"name":"Obere Kreisstr.","postalCode":"06493","locality":"Harzgerode","municipality":{"key":"15085145","name":"Harzgerode, Stadt","type":"Stadt"},"district":{"key":"15085","name":"Harz","type":"Landkreis"},"federalState":{"key":"15","name":"Sachsen-Anhalt"}},{"name":"Obere Krodostr.","postalCode":"38667","locality":"Bad Harzburg","municipality":{"key":"03153002","name":"Bad Harzburg, Stadt","type":"Stadt"},"district":{"key":"03153","name":"Goslar","type":"Landkreis"},"federalState":{"key":"03","name":"Niedersachsen"}},{"name":"Obere Mühlen Str.","postalCode":"37520","locality":"Osterode am Harz","municipality":{"key":"03159026","name":"Osterode am Harz, Stadt","type":"Stadt"},"district":{"key":"03159","name":"Göttingen","type":"Landkreis"},"federalState":{"key":"03","name":"Niedersachsen"}},{"name":"Oberer Adenbergweg","postalCode":"38667","locality":"Harz (LK Goslar)","municipality":{"key":"03153504","name":"Harz (Landkreis Goslar), gemfr. Gebiet","type":"Gemeindefreies_Gebiet_Unbewohnt"},"district":{"key":"03153","name":"Goslar","type":"Landkreis"},"federalState":{"key":"03","name":"Niedersachsen"}},{"name":"Oberer Bandweg","postalCode":"06536","locality":"Südharz","municipality":{"key":"15087412","name":"Südharz","type":"Kreisangehörige_Gemeinde"},"district":{"key":"15087","name":"Mansfeld-Südharz","type":"Landkreis"},"federalState":{"key":"15","name":"Sachsen-Anhalt"}},{"name":"Oberer Bleicheweg","postalCode":"38667","locality":"Harz (LK Goslar)","municipality":{"key":"03153504","name":"Harz (Landkreis Goslar), gemfr. Gebiet","type":"Gemeindefreies_Gebiet_Unbewohnt"},"district":{"key":"03153","name":"Goslar","type":"Landkreis"},"federalState":{"key":"03","name":"Niedersachsen"}},{"name":"Oberer Bruchbergweg","postalCode":"38707","locality":"Harz (LK Goslar)","municipality":{"key":"03153504","name":"Harz (Landkreis Goslar), gemfr. Gebiet","type":"Gemeindefreies_Gebiet_Unbewohnt"},"district":{"key":"03153","name":"Goslar","type":"Landkreis"},"federalState":{"key":"03","name":"Niedersachsen"}},{"name":"Oberer Eichenbergsweg","postalCode":"38723","locality":"Harz (LK Goslar)","municipality":{"key":"03153504","name":"Harz (Landkreis Goslar), gemfr. Gebiet","type":"Gemeindefreies_Gebiet_Unbewohnt"},"district":{"key":"03153","name":"Goslar","type":"Landkreis"},"federalState":{"key":"03","name":"Niedersachsen"}},{"name":"Obere Reihe","postalCode":"99768","locality":"Harztor","municipality":{"key":"16062065","name":"Harztor","type":"Kreisangehörige_Gemeinde"},"district":{"key":"16062","name":"Nordhausen","type":"Landkreis"},"federalState":{"key":"16","name":"Thüringen"}},{"name":"Oberer Hahnenkopf","postalCode":"38889","locality":"Oberharz am Brocken","municipality":{"key":"15085228","name":"Oberharz am Brocken, Stadt","type":"Stadt"},"district":{"key":"15085","name":"Harz","type":"Landkreis"},"federalState":{"key":"15","name":"Sachsen-Anhalt"}},{"name":"Oberer Kahlenberg","postalCode":"38875","locality":"Oberharz am Brocken","municipality":{"key":"15085228","name":"Oberharz am Brocken, Stadt","type":"Stadt"},"district":{"key":"15085","name":"Harz","type":"Landkreis"},"federalState":{"key":"15","name":"Sachsen-Anhalt"}},{"name":"Oberer Mühlengraben","postalCode":"37412","locality":"Herzberg am Harz","municipality":{"key":"03159019","name":"Herzberg am Harz, Stadt","type":"Stadt"},"district":{"key":"03159","name":"Göttingen","type":"Landkreis"},"federalState":{"key":"03","name":"Niedersachsen"}},{"name":"Oberer Oderweg","postalCode":"37444","locality":"Harz (LK Goslar)","municipality":{"key":"03153504","name":"Harz (Landkreis Goslar), gemfr. Gebiet","type":"Gemeindefreies_Gebiet_Unbewohnt"},"district":{"key":"03153","name":"Goslar","type":"Landkreis"},"federalState":{"key":"03","name":"Niedersachsen"}},{"name":"Oberer Ortberg","postalCode":"38875","locality":"Oberharz am Brocken","municipality":{"key":"15085228","name":"Oberharz am Brocken, Stadt","type":"Stadt"},"district":{"key":"15085","name":"Harz","type":"Landkreis"},"federalState":{"key":"15","name":"Sachsen-Anhalt"}},{"name":"Oberer Reupersbergweg","postalCode":"37431","locality":"Harz (Landkreis Göttingen)","municipality":{"key":"03159501","name":"Harz (Landkreis Göttingen), gemfr. Geb.","type":"Gemeindefreies_Gebiet_Unbewohnt"},"district":{"key":"03159","name":"Göttingen","type":"Landkreis"},"federalState":{"key":"03","name":"Niedersachsen"}},{"name":"Oberer Ristchenweg","postalCode":"37520","locality":"Osterode am Harz","municipality":{"key":"03159026","name":"Osterode am Harz, Stadt","type":"Stadt"},"district":{"key":"03159","name":"Göttingen","type":"Landkreis"},"federalState":{"key":"03","name":"Niedersachsen"}},{"name":"Oberer Romkerkopfweg","postalCode":"38667","locality":"Harz (LK Goslar)","municipality":{"key":"03153504","name":"Harz (Landkreis Goslar), gemfr. Gebiet","type":"Gemeindefreies_Gebiet_Unbewohnt"},"district":{"key":"03153","name":"Goslar","type":"Landkreis"},"federalState":{"key":"03","name":"Niedersachsen"}},{"name":"Oberer Schlufterkopfweg","postalCode":"37520","locality":"Harz (Landkreis Göttingen)","municipality":{"key":"03159501","name":"Harz (Landkreis Göttingen), gemfr. Geb.","type":"Gemeindefreies_Gebiet_Unbewohnt"},"district":{"key":"03159","name":"Göttingen","type":"Landkreis"},"federalState":{"key":"03","name":"Niedersachsen"}},{"name":"Oberer Scholbenweg","postalCode":"37431","locality":"Harz (Landkreis Göttingen)","municipality":{"key":"03159501","name":"Harz (Landkreis Göttingen), gemfr. Geb.","type":"Gemeindefreies_Gebiet_Unbewohnt"},"district":{"key":"03159","name":"Göttingen","type":"Landkreis"},"federalState":{"key":"03","name":"Niedersachsen"}},{"name":"Oberer Schweinetalweg","postalCode":"37444","locality":"Harz (LK Goslar)","municipality":{"key":"03153504","name":"Harz (Landkreis Goslar), gemfr. Gebiet","type":"Gemeindefreies_Gebiet_Unbewohnt"},"district":{"key":"03153","name":"Goslar","type":"Landkreis"},"federalState":{"key":"03","name":"Niedersachsen"}},{"name":"Oberer Sieberweg","postalCode":"37412","locality":"Herzberg am Harz","municipality":{"key":"03159019","name":"Herzberg am Harz, Stadt","type":"Stadt"},"district":{"key":"03159","name":"Göttingen","type":"Landkreis"},"federalState":{"key":"03","name":"Niedersachsen"}},{"name":"Oberer Siegen","postalCode":"06536","locality":"Südharz","municipality":{"key":"15087412","name":"Südharz","type":"Kreisangehörige_Gemeinde"},"district":{"key":"15087","name":"Mansfeld-Südharz","type":"Landkreis"},"federalState":{"key":"15","name":"Sachsen-Anhalt"}},{"name":"Oberer Teichtalsweg","postalCode":"37412","locality":"Harz (Landkreis Göttingen)","municipality":{"key":"03159501","name":"Harz (Landkreis Göttingen), gemfr. Geb.","type":"Gemeindefreies_Gebiet_Unbewohnt"},"district":{"key":"03159","name":"Göttingen","type":"Landkreis"},"federalState":{"key":"03","name":"Niedersachsen"}},{"name":"Oberer Weg","postalCode":"37520","locality":"Osterode am Harz","municipality":{"key":"03159026","name":"Osterode am Harz, Stadt","type":"Stadt"},"district":{"key":"03159","name":"Göttingen","type":"Landkreis"},"federalState":{"key":"03","name":"Niedersachsen"}},{"name":"Obere Schacht","postalCode":"37520","locality":"Osterode am Harz","municipality":{"key":"03159026","name":"Osterode am Harz, Stadt","type":"Stadt"},"district":{"key":"03159","name":"Göttingen","type":"Landkreis"},"federalState":{"key":"03","name":"Niedersachsen"}},{"name":"Obere Schulstr.","postalCode":"38875","locality":"Oberharz am Brocken","municipality":{"key":"15085228","name":"Oberharz am Brocken, Stadt","type":"Stadt"},"district":{"key":"15085","name":"Harz","type":"Landkreis"},"federalState":{"key":"15","name":"Sachsen-Anhalt"}},{"name":"Obere Steinbreite","postalCode":"37520","locality":"Osterode am Harz","municipality":{"key":"03159026","name":"Osterode am Harz, Stadt","type":"Stadt"},"district":{"key":"03159","name":"Göttingen","type":"Landkreis"},"federalState":{"key":"03","name":"Niedersachsen"}},{"name":"Obere Str.","postalCode":"37199","locality":"Wulften am Harz","municipality":{"key":"03159039","name":"Wulften am Harz","type":"Kreisangehörige_Gemeinde"},"district":{"key":"03159","name":"Göttingen","type":"Landkreis"},"federalState":{"key":"03","name":"Niedersachsen"}},{"name":"Obere Wassergasse","postalCode":"37412","locality":"Herzberg am Harz","municipality":{"key":"03159019","name":"Herzberg am Harz, Stadt","type":"Stadt"},"district":{"key":"03159","name":"Göttingen","type":"Landkreis"},"federalState":{"key":"03","name":"Niedersachsen"}},{"name":"Oberförster-Hahn-Weg","postalCode":"38723","locality":"Harz (LK Goslar)","municipality":{"key":"03153504","name":"Harz (Landkreis Goslar), gemfr. Gebiet","type":"Gemeindefreies_Gebiet_Unbewohnt"},"district":{"key":"03153","name":"Goslar","type":"Landkreis"},"federalState":{"key":"03","name":"Niedersachsen"}},{"name":"Oberförster-Hinze-Weg","postalCode":"38723","locality":"Harz (LK Goslar)","municipality":{"key":"03153504","name":"Harz (Landkreis Goslar), gemfr. Gebiet","type":"Gemeindefreies_Gebiet_Unbewohnt"},"district":{"key":"03153","name":"Goslar","type":"Landkreis"},"federalState":{"key":"03","name":"Niedersachsen"}},{"name":"Oberförsterweg","postalCode":"38899","locality":"Oberharz am Brocken","municipality":{"key":"15085228","name":"Oberharz am Brocken, Stadt","type":"Stadt"},"district":{"key":"15085","name":"Harz","type":"Landkreis"},"federalState":{"key":"15","name":"Sachsen-Anhalt"}},{"name":"Oberhofer Str.","postalCode":"99897","locality":"Tambach-Dietharz","municipality":{"key":"16067065","name":"Tambach-Dietharz/Thür. Wald, Stadt","type":"Stadt"},"district":{"key":"16067","name":"Gotha","type":"Landkreis"},"federalState":{"key":"16","name":"Thüringen"}},{"name":"Oberstadt","postalCode":"38877","locality":"Oberharz am Brocken","municipality":{"key":"15085228","name":"Oberharz am Brocken, Stadt","type":"Stadt"},"district":{"key":"15085","name":"Harz","type":"Landkreis"},"federalState":{"key":"15","name":"Sachsen-Anhalt"}},{"name":"Oberstr.","postalCode":"06493","locality":"Harzgerode","municipality":{"key":"15085145","name":"Harzgerode, Stadt","type":"Stadt"},"district":{"key":"15085","name":"Harz","type":"Landkreis"},"federalState":{"key":"15","name":"Sachsen-Anhalt"}},{"name":"Planstr.","postalCode":"06458","locality":"Hedersleben","municipality":{"key":"15085160","name":"Hedersleben","type":"Kreisangehörige_Gemeinde"},"district":{"key":"15085","name":"Harz","type":"Landkreis"},"federalState":{"key":"15","name":"Sachsen-Anhalt"}},{"name":"Quedlinburger Str.","postalCode":"06458","locality":"Hedersleben","municipality":{"key":"15085160","name":"Hedersleben","type":"Kreisangehörige_Gemeinde"},"district":{"key":"15085","name":"Harz","type":"Landkreis"},"federalState":{"key":"15","name":"Sachsen-Anhalt"}},{"name":"Ritterstr.","postalCode":"06458","locality":"Hedersleben","municipality":{"key":"15085160","name":"Hedersleben","type":"Kreisangehörige_Gemeinde"},"district":{"key":"15085","name":"Harz","type":"Landkreis"},"federalState":{"key":"15","name":"Sachsen-Anhalt"}},{"name":"Schadelebener Weg","postalCode":"06458","locality":"Hedersleben","municipality":{"key":"15085160","name":"Hedersleben","type":"Kreisangehörige_Gemeinde"},"district":{"key":"15085","name":"Harz","type":"Landkreis"},"federalState":{"key":"15","name":"Sachsen-Anhalt"}},{"name":"Schmale Str.","postalCode":"06458","locality":"Hedersleben","municipality":{"key":"15085160","name":"Hedersleben","type":"Kreisangehörige_Gemeinde"},"district":{"key":"15085","name":"Harz","type":"Landkreis"},"federalState":{"key":"15","name":"Sachsen-Anhalt"}},{"name":"Schuhhof","postalCode":"06458","locality":"Hedersleben","municipality":{"key":"15085160","name":"Hedersleben","type":"Kreisangehörige_Gemeinde"},"district":{"key":"15085","name":"Harz","type":"Landkreis"},"federalState":{"key":"15","name":"Sachsen-Anhalt"}},{"name":"Schulstr.","postalCode":"06458","locality":"Hedersleben","municipality":{"key":"15085160","name":"Hedersleben","type":"Kreisangehörige_Gemeinde"},"district":{"key":"15085","name":"Harz","type":"Landkreis"},"federalState":{"key":"15","name":"Sachsen-Anhalt"}},{"name":"Schützenstr.","postalCode":"06458","locality":"Hedersleben","municipality":{"key":"15085160","name":"Hedersleben","type":"Kreisangehörige_Gemeinde"},"district":{"key":"15085","name":"Harz","type":"Landkreis"},"federalState":{"key":"15","name":"Sachsen-Anhalt"}},{"name":"Siedlung","postalCode":"06458","locality":"Hedersleben","municipality":{"key":"15085160","name":"Hedersleben","type":"Kreisangehörige_Gemeinde"},"district":{"key":"15085","name":"Harz","type":"Landkreis"},"federalState":{"key":"15","name":"Sachsen-Anhalt"}},{"name":"Stegstr.","postalCode":"06458","locality":"Hedersleben","municipality":{"key":"15085160","name":"Hedersleben","type":"Kreisangehörige_Gemeinde"},"district":{"key":"15085","name":"Harz","type":"Landkreis"},"federalState":{"key":"15","name":"Sachsen-Anhalt"}},{"name":"Tieforte","postalCode":"06458","locality":"Hedersleben","municipality":{"key":"15085160","name":"Hedersleben","type":"Kreisangehörige_Gemeinde"},"district":{"key":"15085","name":"Harz","type":"Landkreis"},"federalState":{"key":"15","name":"Sachsen-Anhalt"}},{"name":"Tiefortenstr.","postalCode":"06458","locality":"Hedersleben","municipality":{"key":"15085160","name":"Hedersleben","type":"Kreisangehörige_Gemeinde"},"district":{"key":"15085","name":"Harz","type":"Landkreis"},"federalState":{"key":"15","name":"Sachsen-Anhalt"}},{"name":"Uferstr.","postalCode":"37197","locality":"Hattorf am Harz","municipality":{"key":"03159018","name":"Hattorf am Harz","type":"Kreisangehörige_Gemeinde"},"district":{"key":"03159","name":"Göttingen","type":"Landkreis"},"federalState":{"key":"03","name":"Niedersachsen"}},{"name":"Uferstr.","postalCode":"37199","locality":"Wulften am Harz","municipality":{"key":"03159039","name":"Wulften am Harz","type":"Kreisangehörige_Gemeinde"},"district":{"key":"03159","name":"Göttingen","type":"Landkreis"},"federalState":{"key":"03","name":"Niedersachsen"}},{"name":"Uferstr.","postalCode":"37431","locality":"Bad Lauterberg im Harz","municipality":{"key":"03159003","name":"Bad Lauterberg im Harz, Stadt","type":"Stadt"},"district":{"key":"03159","name":"Göttingen","type":"Landkreis"},"federalState":{"key":"03","name":"Niedersachsen"}},{"name":"Uferstr.","postalCode":"99768","locality":"Harztor","municipality":{"key":"16062065","name":"Harztor","type":"Kreisangehörige_Gemeinde"},"district":{"key":"16062","name":"Nordhausen","type":"Landkreis"},"federalState":{"key":"16","name":"Thüringen"}},{"name":"Uftrunger Enge Gasse","postalCode":"06536","locality":"Südharz","municipality":{"key":"15087412","name":"Südharz","type":"Kreisangehörige_Gemeinde"},"district":{"key":"15087","name":"Mansfeld-Südharz","type":"Landkreis"},"federalState":{"key":"15","name":"Sachsen-Anhalt"}},{"name":"Uftrunger Feldstr.","postalCode":"06536","locality":"Südharz","municipality":{"key":"15087412","name":"Südharz","type":"Kreisangehörige_Gemeinde"},"district":{"key":"15087","name":"Mansfeld-Südharz","type":"Landkreis"},"federalState":{"key":"15","name":"Sachsen-Anhalt"}},{"name":"Uftrunger Hauptstr.","postalCode":"06536","locality":"Südharz","municipality":{"key":"15087412","name":"Südharz","type":"Kreisangehörige_Gemeinde"},"district":{"key":"15087","name":"Mansfeld-Südharz","type":"Landkreis"},"federalState":{"key":"15","name":"Sachsen-Anhalt"}},{"name":"Uftrunger Schulgasse","postalCode":"06536","locality":"Südharz","municipality":{"key":"15087412","name":"Südharz","type":"Kreisangehörige_Gemeinde"},"district":{"key":"15087","name":"Mansfeld-Südharz","type":"Landkreis"},"federalState":{"key":"15","name":"Sachsen-Anhalt"}},{"name":"Uftrunger Teichdamm","postalCode":"06536","locality":"Südharz","municipality":{"key":"15087412","name":"Südharz","type":"Kreisangehörige_Gemeinde"},"district":{"key":"15087","name":"Mansfeld-Südharz","type":"Landkreis"},"federalState":{"key":"15","name":"Sachsen-Anhalt"}},{"name":"Uhlenweg","postalCode":"38667","locality":"Bad Harzburg","municipality":{"key":"03153002","name":"Bad Harzburg, Stadt","type":"Stadt"},"district":{"key":"03153","name":"Goslar","type":"Landkreis"},"federalState":{"key":"03","name":"Niedersachsen"}},{"name":"Ulmenstr.","postalCode":"37412","locality":"Herzberg am Harz","municipality":{"key":"03159019","name":"Herzberg am Harz, Stadt","type":"Stadt"},"district":{"key":"03159","name":"Göttingen","type":"Landkreis"},"federalState":{"key":"03","name":"Niedersachsen"}},{"name":"Ulmenstr.","postalCode":"37431","locality":"Bad Lauterberg im Harz","municipality":{"key":"03159003","name":"Bad Lauterberg im Harz, Stadt","type":"Stadt"},"district":{"key":"03159","name":"Göttingen","type":"Landkreis"},"federalState":{"key":"03","name":"Niedersachsen"}},{"name":"Ulmenweg","postalCode":"37520","locality":"Osterode am Harz","municipality":{"key":"03159026","name":"Osterode am Harz, Stadt","type":"Stadt"},"district":{"key":"03159","name":"Göttingen","type":"Landkreis"},"federalState":{"key":"03","name":"Niedersachsen"}},{"name":"Ulmer Weg","postalCode":"37520","locality":"Harz (Landkreis Göttingen)","municipality":{"key":"03159501","name":"Harz (Landkreis Göttingen), gemfr. Geb.","type":"Gemeindefreies_Gebiet_Unbewohnt"},"district":{"key":"03159","name":"Göttingen","type":"Landkreis"},"federalState":{"key":"03","name":"Niedersachsen"}},{"name":"Ulmer Weg","postalCode":"38667","locality":"Harz (LK Goslar)","municipality":{"key":"03153504","name":"Harz (Landkreis Goslar), gemfr. Gebiet","type":"Gemeindefreies_Gebiet_Unbewohnt"},"district":{"key":"03153","name":"Goslar","type":"Landkreis"},"federalState":{"key":"03","name":"Niedersachsen"}},{"name":"Ulmer Weg","postalCode":"38700","locality":"Harz (LK Goslar)","municipality":{"key":"03153504","name":"Harz (Landkreis Goslar), gemfr. Gebiet","type":"Gemeindefreies_Gebiet_Unbewohnt"},"district":{"key":"03153","name":"Goslar","type":"Landkreis"},"federalState":{"key":"03","name":"Niedersachsen"}},{"name":"Ulmer Weg","postalCode":"38875","locality":"Oberharz am Brocken","municipality":{"key":"15085228","name":"Oberharz am Brocken, Stadt","type":"Stadt"},"district":{"key":"15085","name":"Harz","type":"Landkreis"},"federalState":{"key":"15","name":"Sachsen-Anhalt"}},{"name":"Ulrichstal","postalCode":"37445","locality":"Harz (Landkreis Göttingen)","municipality":{"key":"03159501","name":"Harz (Landkreis Göttingen), gemfr. Geb.","type":"Gemeindefreies_Gebiet_Unbewohnt"},"district":{"key":"03159","name":"Göttingen","type":"Landkreis"},"federalState":{"key":"03","name":"Niedersachsen"}},{"name":"Unterbruch","postalCode":"38877","locality":"Oberharz am Brocken","municipality":{"key":"15085228","name":"Oberharz am Brocken, Stadt","type":"Stadt"},"district":{"key":"15085","name":"Harz","type":"Landkreis"},"federalState":{"key":"15","name":"Sachsen-Anhalt"}},{"name":"Unter dem Branntweinstein","postalCode":"37520","locality":"Osterode am Harz","municipality":{"key":"03159026","name":"Osterode am Harz, Stadt","type":"Stadt"},"district":{"key":"03159","name":"Göttingen","type":"Landkreis"},"federalState":{"key":"03","name":"Niedersachsen"}},{"name":"Unter dem Kleiberg","postalCode":"37412","locality":"Hörden am Harz","municipality":{"key":"03159020","name":"Hörden am Harz","type":"Kreisangehörige_Gemeinde"},"district":{"key":"03159","name":"Göttingen","type":"Landkreis"},"federalState":{"key":"03","name":"Niedersachsen"}},{"name":"Unter den Birken","postalCode":"38875","locality":"Oberharz am Brocken","municipality":{"key":"15085228","name":"Oberharz am Brocken, Stadt","type":"Stadt"},"district":{"key":"15085","name":"Harz","type":"Landkreis"},"federalState":{"key":"15","name":"Sachsen-Anhalt"}},{"name":"Unter den Eichen","postalCode":"37197","locality":"Hattorf am Harz","municipality":{"key":"03159018","name":"Hattorf am Harz","type":"Kreisangehörige_Gemeinde"},"district":{"key":"03159","name":"Göttingen","type":"Landkreis"},"federalState":{"key":"03","name":"Niedersachsen"}},{"name":"Unter den Eichen","postalCode":"38667","locality":"Bad Harzburg","municipality":{"key":"03153002","name":"Bad Harzburg, Stadt","type":"Stadt"},"district":{"key":"03153","name":"Goslar","type":"Landkreis"},"federalState":{"key":"03","name":"Niedersachsen"}},{"name":"Unter den Linden","postalCode":"38667","locality":"Bad Harzburg","municipality":{"key":"03153002","name":"Bad Harzburg, Stadt","type":"Stadt"},"district":{"key":"03153","name":"Goslar","type":"Landkreis"},"federalState":{"key":"03","name":"Niedersachsen"}},{"name":"Unterdorf","postalCode":"06463","locality":"Falkenstein/Harz","municipality":{"key":"15085110","name":"Falkenstein/Harz, Stadt","type":"Stadt"},"district":{"key":"15085","name":"Harz","type":"Landkreis"},"federalState":{"key":"15","name":"Sachsen-Anhalt"}},{"name":"Unterdorf","postalCode":"06543","locality":"Falkenstein/Harz","municipality":{"key":"15085110","name":"Falkenstein/Harz, Stadt","type":"Stadt"},"district":{"key":"15085","name":"Harz","type":"Landkreis"},"federalState":{"key":"15","name":"Sachsen-Anhalt"}},{"name":"Unterdorf","postalCode":"37199","locality":"Wulften am Harz","municipality":{"key":"03159039","name":"Wulften am Harz","type":"Kreisangehörige_Gemeinde"},"district":{"key":"03159","name":"Göttingen","type":"Landkreis"},"federalState":{"key":"03","name":"Niedersachsen"}},{"name":"Unterdorf","postalCode":"37412","locality":"Herzberg am Harz","municipality":{"key":"03159019","name":"Herzberg am Harz, Stadt","type":"Stadt"},"district":{"key":"03159","name":"Göttingen","type":"Landkreis"},"federalState":{"key":"03","name":"Niedersachsen"}},{"name":"Unterdorf","postalCode":"37520","locality":"Osterode am Harz","municipality":{"key":"03159026","name":"Osterode am Harz, Stadt","type":"Stadt"},"district":{"key":"03159","name":"Göttingen","type":"Landkreis"},"federalState":{"key":"03","name":"Niedersachsen"}},{"name":"Untere Gasse","postalCode":"06536","locality":"Südharz","municipality":{"key":"15087412","name":"Südharz","type":"Kreisangehörige_Gemeinde"},"district":{"key":"15087","name":"Mansfeld-Südharz","type":"Landkreis"},"federalState":{"key":"15","name":"Sachsen-Anhalt"}},{"name":"Untere Gasse","postalCode":"06543","locality":"Falkenstein/Harz","municipality":{"key":"15085110","name":"Falkenstein/Harz, Stadt","type":"Stadt"},"district":{"key":"15085","name":"Harz","type":"Landkreis"},"federalState":{"key":"15","name":"Sachsen-Anhalt"}},{"name":"Untere Hauptstr.","postalCode":"06333","locality":"Falkenstein/Harz","municipality":{"key":"15085110","name":"Falkenstein/Harz, Stadt","type":"Stadt"},"district":{"key":"15085","name":"Harz","type":"Landkreis"},"federalState":{"key":"15","name":"Sachsen-Anhalt"}},{"name":"Untere Herrentalstr.","postalCode":"37520","locality":"Osterode am Harz","municipality":{"key":"03159026","name":"Osterode am Harz, Stadt","type":"Stadt"},"district":{"key":"03159","name":"Göttingen","type":"Landkreis"},"federalState":{"key":"03","name":"Niedersachsen"}},{"name":"Untere Hofbreite","postalCode":"38667","locality":"Bad Harzburg","municipality":{"key":"03153002","name":"Bad Harzburg, Stadt","type":"Stadt"},"district":{"key":"03153","name":"Goslar","type":"Landkreis"},"federalState":{"key":"03","name":"Niedersachsen"}},{"name":"Untere Kreisstr.","postalCode":"06493","locality":"Harzgerode","municipality":{"key":"15085145","name":"Harzgerode, Stadt","type":"Stadt"},"district":{"key":"15085","name":"Harz","type":"Landkreis"},"federalState":{"key":"15","name":"Sachsen-Anhalt"}},{"name":"Untere Krodostr.","postalCode":"38667","locality":"Bad Harzburg","municipality":{"key":"03153002","name":"Bad Harzburg, Stadt","type":"Stadt"},"district":{"key":"03153","name":"Goslar","type":"Landkreis"},"federalState":{"key":"03","name":"Niedersachsen"}},{"name":"Untere Neustadt","postalCode":"37520","locality":"Osterode am Harz","municipality":{"key":"03159026","name":"Osterode am Harz, Stadt","type":"Stadt"},"district":{"key":"03159","name":"Göttingen","type":"Landkreis"},"federalState":{"key":"03","name":"Niedersachsen"}},{"name":"Unterer Adenbergweg","postalCode":"38667","locality":"Harz (LK Goslar)","municipality":{"key":"03153504","name":"Harz (Landkreis Goslar), gemfr. Gebiet","type":"Gemeindefreies_Gebiet_Unbewohnt"},"district":{"key":"03153","name":"Goslar","type":"Landkreis"},"federalState":{"key":"03","name":"Niedersachsen"}},{"name":"Unterer Bruchbergweg","postalCode":"38707","locality":"Harz (LK Goslar)","municipality":{"key":"03153504","name":"Harz (Landkreis Goslar), gemfr. Gebiet","type":"Gemeindefreies_Gebiet_Unbewohnt"},"district":{"key":"03153","name":"Goslar","type":"Landkreis"},"federalState":{"key":"03","name":"Niedersachsen"}},{"name":"Unterer Eichenbergsweg","postalCode":"38723","locality":"Harz (LK Goslar)","municipality":{"key":"03153504","name":"Harz (Landkreis Goslar), gemfr. Gebiet","type":"Gemeindefreies_Gebiet_Unbewohnt"},"district":{"key":"03153","name":"Goslar","type":"Landkreis"},"federalState":{"key":"03","name":"Niedersachsen"}},{"name":"Untere Reihe","postalCode":"99768","locality":"Harztor","municipality":{"key":"16062065","name":"Harztor","type":"Kreisangehörige_Gemeinde"},"district":{"key":"16062","name":"Nordhausen","type":"Landkreis"},"federalState":{"key":"16","name":"Thüringen"}},{"name":"Unterer Fußstieg","postalCode":"06536","locality":"Südharz","municipality":{"key":"15087412","name":"Südharz","type":"Kreisangehörige_Gemeinde"},"district":{"key":"15087","name":"Mansfeld-Südharz","type":"Landkreis"},"federalState":{"key":"15","name":"Sachsen-Anhalt"}},{"name":"Unterer Hahnenkopf","postalCode":"38889","locality":"Oberharz am Brocken","municipality":{"key":"15085228","name":"Oberharz am Brocken, Stadt","type":"Stadt"},"district":{"key":"15085","name":"Harz","type":"Landkreis"},"federalState":{"key":"15","name":"Sachsen-Anhalt"}},{"name":"Unterer Herrenweg","postalCode":"38667","locality":"Harz (LK Goslar)","municipality":{"key":"03153504","name":"Harz (Landkreis Goslar), gemfr. Gebiet","type":"Gemeindefreies_Gebiet_Unbewohnt"},"district":{"key":"03153","name":"Goslar","type":"Landkreis"},"federalState":{"key":"03","name":"Niedersachsen"}},{"name":"Unterer Horizontalweg","postalCode":"38700","locality":"Harz (LK Goslar)","municipality":{"key":"03153504","name":"Harz (Landkreis Goslar), gemfr. Gebiet","type":"Gemeindefreies_Gebiet_Unbewohnt"},"district":{"key":"03153","name":"Goslar","type":"Landkreis"},"federalState":{"key":"03","name":"Niedersachsen"}},{"name":"Unterer Kahbergsweg","postalCode":"38667","locality":"Harz (LK Goslar)","municipality":{"key":"03153504","name":"Harz (Landkreis Goslar), gemfr. Gebiet","type":"Gemeindefreies_Gebiet_Unbewohnt"},"district":{"key":"03153","name":"Goslar","type":"Landkreis"},"federalState":{"key":"03","name":"Niedersachsen"}},{"name":"Unterer Kahlenberg","postalCode":"38875","locality":"Oberharz am Brocken","municipality":{"key":"15085228","name":"Oberharz am Brocken, Stadt","type":"Stadt"},"district":{"key":"15085","name":"Harz","type":"Landkreis"},"federalState":{"key":"15","name":"Sachsen-Anhalt"}},{"name":"Unterer Kuxstein","postalCode":"06536","locality":"Südharz","municipality":{"key":"15087412","name":"Südharz","type":"Kreisangehörige_Gemeinde"},"district":{"key":"15087","name":"Mansfeld-Südharz","type":"Landkreis"},"federalState":{"key":"15","name":"Sachsen-Anhalt"}},{"name":"Unterer Oderweg","postalCode":"37444","locality":"Harz (LK Goslar)","municipality":{"key":"03153504","name":"Harz (Landkreis Goslar), gemfr. Gebiet","type":"Gemeindefreies_Gebiet_Unbewohnt"},"district":{"key":"03153","name":"Goslar","type":"Landkreis"},"federalState":{"key":"03","name":"Niedersachsen"}},{"name":"Verlorener Weg","postalCode":"06458","locality":"Hedersleben","municipality":{"key":"15085160","name":"Hedersleben","type":"Kreisangehörige_Gemeinde"},"district":{"key":"15085","name":"Harz","type":"Landkreis"},"federalState":{"key":"15","name":"Sachsen-Anhalt"}},{"name":"Wasserstr.","postalCode":"06458","locality":"Hedersleben","municipality":{"key":"15085160","name":"Hedersleben","type":"Kreisangehörige_Gemeinde"},"district":{"key":"15085","name":"Harz","type":"Landkreis"},"federalState":{"key":"15","name":"Sachsen-Anhalt"}},{"name":"Winkelbreite","postalCode":"06458","locality":"Hedersleben","municipality":{"key":"15085160","name":"Hedersleben","type":"Kreisangehörige_Gemeinde"},"district":{"key":"15085","name":"Harz","type":"Landkreis"},"federalState":{"key":"15","name":"Sachsen-Anhalt"}},{"name":"zur Selkemündung","postalCode":"06458","locality":"Hedersleben","municipality":{"key":"15085160","name":"Hedersleben","type":"Kreisangehörige_Gemeinde"},"district":{"key":"15085","name":"Harz","type":"Landkreis"},"federalState":{"key":"15","name":"Sachsen-Anhalt"}},{"name":"Öhrentalsweg","postalCode":"38667","locality":"Harz (LK Goslar)","municipality":{"key":"03153504","name":"Harz (Landkreis Goslar), gemfr. Gebiet","type":"Gemeindefreies_Gebiet_Unbewohnt"},"district":{"key":"03153","name":"Goslar","type":"Landkreis"},"federalState":{"key":"03","name":"Niedersachsen"}},{"name":"Ölmühle","postalCode":"06536","locality":"Südharz","municipality":{"key":"15087412","name":"Südharz","type":"Kreisangehörige_Gemeinde"},"district":{"key":"15087","name":"Mansfeld-Südharz","type":"Landkreis"},"federalState":{"key":"15","name":"Sachsen-Anhalt"}},{"name":"Ölmühle","postalCode":"37199","locality":"Wulften am Harz","municipality":{"key":"03159039","name":"Wulften am Harz","type":"Kreisangehörige_Gemeinde"},"district":{"key":"03159","name":"Göttingen","type":"Landkreis"},"federalState":{"key":"03","name":"Niedersachsen"}},{"name":"Ölmühlengasse","postalCode":"37520","locality":"Osterode am Harz","municipality":{"key":"03159026","name":"Osterode am Harz, Stadt","type":"Stadt"},"district":{"key":"03159","name":"Göttingen","type":"Landkreis"},"federalState":{"key":"03","name":"Niedersachsen"}},{"name":"Ölmühlenweg","postalCode":"06493","locality":"Harzgerode","municipality":{"key":"15085145","name":"Harzgerode, Stadt","type":"Stadt"},"district":{"key":"15085","name":"Harz","type":"Landkreis"},"federalState":{"key":"15","name":"Sachsen-Anhalt"}},{"name":"Übelsbergweg","postalCode":"37431","locality":"Harz (Landkreis Göttingen)","municipality":{"key":"03159501","name":"Harz (Landkreis Göttingen), gemfr. Geb.","type":"Gemeindefreies_Gebiet_Unbewohnt"},"district":{"key":"03159","name":"Göttingen","type":"Landkreis"},"federalState":{"key":"03","name":"Niedersachsen"}},{"name":"Über der Flut","postalCode":"37431","locality":"Bad Lauterberg im Harz","municipality":{"key":"03159003","name":"Bad Lauterberg im Harz, Stadt","type":"Stadt"},"district":{"key":"03159","name":"Göttingen","type":"Landkreis"},"federalState":{"key":"03","name":"Niedersachsen"}},{"name":"Über der Kälberbucht","postalCode":"37431","locality":"Bad Lauterberg im Harz","municipality":{"key":"03159003","name":"Bad Lauterberg im Harz, Stadt","type":"Stadt"},"district":{"key":"03159","name":"Göttingen","type":"Landkreis"},"federalState":{"key":"03","name":"Niedersachsen"}},{"name":"Ührde","postalCode":"37520","locality":"Osterode am Harz","municipality":{"key":"03159026","name":"Osterode am Harz, Stadt","type":"Stadt"},"district":{"key":"03159","name":"Göttingen","type":"Landkreis"},"federalState":{"key":"03","name":"Niedersachsen"}},{"name":"Ührder Str.","postalCode":"37520","locality":"Osterode am Harz","municipality":{"key":"03159026","name":"Osterode am Harz, Stadt","type":"Stadt"},"district":{"key":"03159","name":"Göttingen","type":"Landkreis"},"federalState":{"key":"03","name":"Niedersachsen"}},]