[{"name":"Adelbergstr.","postalCode":"88138","locality":"Sigmarszell","municipality":{"key":"09776126","name":"Sigmarszell","type":"Kreisangehörige_Gemeinde"},"district":{"key":"09776","name":"Lindau (Bodensee)","type":"Landkreis"},"federalState":{"key":"09","name":"Bayern"}},{"name":"Allgäustr.","postalCode":"88138","locality":"Sigmarszell","municipality":{"key":"09776126","name":"Sigmarszell","type":"Kreisangehörige_Gemeinde"},"district":{"key":"09776","name":"Lindau (Bodensee)","type":"Landkreis"},"federalState":{"key":"09","name":"Bayern"}},{"name":"Am Knobel","postalCode":"88138","locality":"Sigmarszell","municipality":{"key":"09776126","name":"Sigmarszell","type":"Kreisangehörige_Gemeinde"},"district":{"key":"09776","name":"Lindau (Bodensee)","type":"Landkreis"},"federalState":{"key":"09","name":"Bayern"}},{"name":"An der Halde","postalCode":"88138","locality":"Sigmarszell","municipality":{"key":"09776126","name":"Sigmarszell","type":"Kreisangehörige_Gemeinde"},"district":{"key":"09776","name":"Lindau (Bodensee)","type":"Landkreis"},"federalState":{"key":"09","name":"Bayern"}},{"name":"An der Obstbauschule","postalCode":"88138","locality":"Sigmarszell","municipality":{"key":"09776126","name":"Sigmarszell","type":"Kreisangehörige_Gemeinde"},"district":{"key":"09776","name":"Lindau (Bodensee)","type":"Landkreis"},"federalState":{"key":"09","name":"Bayern"}},{"name":"Auf der Scheibe","postalCode":"88138","locality":"Sigmarszell","municipality":{"key":"09776126","name":"Sigmarszell","type":"Kreisangehörige_Gemeinde"},"district":{"key":"09776","name":"Lindau (Bodensee)","type":"Landkreis"},"federalState":{"key":"09","name":"Bayern"}},{"name":"Bahnweg","postalCode":"88138","locality":"Sigmarszell","municipality":{"key":"09776126","name":"Sigmarszell","type":"Kreisangehörige_Gemeinde"},"district":{"key":"09776","name":"Lindau (Bodensee)","type":"Landkreis"},"federalState":{"key":"09","name":"Bayern"}},{"name":"Bodenseestr.","postalCode":"88138","locality":"Sigmarszell","municipality":{"key":"09776126","name":"Sigmarszell","type":"Kreisangehörige_Gemeinde"},"district":{"key":"09776","name":"Lindau (Bodensee)","type":"Landkreis"},"federalState":{"key":"09","name":"Bayern"}},{"name":"Burgknobelweg","postalCode":"88138","locality":"Sigmarszell","municipality":{"key":"09776126","name":"Sigmarszell","type":"Kreisangehörige_Gemeinde"},"district":{"key":"09776","name":"Lindau (Bodensee)","type":"Landkreis"},"federalState":{"key":"09","name":"Bayern"}},{"name":"Dornach","postalCode":"88138","locality":"Sigmarszell","municipality":{"key":"09776126","name":"Sigmarszell","type":"Kreisangehörige_Gemeinde"},"district":{"key":"09776","name":"Lindau (Bodensee)","type":"Landkreis"},"federalState":{"key":"09","name":"Bayern"}},{"name":"Egghaldenstr.","postalCode":"88138","locality":"Sigmarszell","municipality":{"key":"09776126","name":"Sigmarszell","type":"Kreisangehörige_Gemeinde"},"district":{"key":"09776","name":"Lindau (Bodensee)","type":"Landkreis"},"federalState":{"key":"09","name":"Bayern"}},{"name":"Egghaldersteig","postalCode":"88138","locality":"Sigmarszell","municipality":{"key":"09776126","name":"Sigmarszell","type":"Kreisangehörige_Gemeinde"},"district":{"key":"09776","name":"Lindau (Bodensee)","type":"Landkreis"},"federalState":{"key":"09","name":"Bayern"}},{"name":"Hauptstr.","postalCode":"88138","locality":"Sigmarszell","municipality":{"key":"09776126","name":"Sigmarszell","type":"Kreisangehörige_Gemeinde"},"district":{"key":"09776","name":"Lindau (Bodensee)","type":"Landkreis"},"federalState":{"key":"09","name":"Bayern"}},{"name":"Heimholzer Str.","postalCode":"88138","locality":"Sigmarszell","municipality":{"key":"09776126","name":"Sigmarszell","type":"Kreisangehörige_Gemeinde"},"district":{"key":"09776","name":"Lindau (Bodensee)","type":"Landkreis"},"federalState":{"key":"09","name":"Bayern"}},{"name":"Hölzlers","postalCode":"88138","locality":"Sigmarszell","municipality":{"key":"09776126","name":"Sigmarszell","type":"Kreisangehörige_Gemeinde"},"district":{"key":"09776","name":"Lindau (Bodensee)","type":"Landkreis"},"federalState":{"key":"09","name":"Bayern"}},{"name":"Im Priel","postalCode":"88138","locality":"Sigmarszell","municipality":{"key":"09776126","name":"Sigmarszell","type":"Kreisangehörige_Gemeinde"},"district":{"key":"09776","name":"Lindau (Bodensee)","type":"Landkreis"},"federalState":{"key":"09","name":"Bayern"}},{"name":"Im Vogelsang","postalCode":"88138","locality":"Sigmarszell","municipality":{"key":"09776126","name":"Sigmarszell","type":"Kreisangehörige_Gemeinde"},"district":{"key":"09776","name":"Lindau (Bodensee)","type":"Landkreis"},"federalState":{"key":"09","name":"Bayern"}},{"name":"In den Osterwiesen","postalCode":"88138","locality":"Sigmarszell","municipality":{"key":"09776126","name":"Sigmarszell","type":"Kreisangehörige_Gemeinde"},"district":{"key":"09776","name":"Lindau (Bodensee)","type":"Landkreis"},"federalState":{"key":"09","name":"Bayern"}},{"name":"Kammbachstr.","postalCode":"88138","locality":"Sigmarszell","municipality":{"key":"09776126","name":"Sigmarszell","type":"Kreisangehörige_Gemeinde"},"district":{"key":"09776","name":"Lindau (Bodensee)","type":"Landkreis"},"federalState":{"key":"09","name":"Bayern"}},{"name":"Leitfritz","postalCode":"88138","locality":"Sigmarszell","municipality":{"key":"09776126","name":"Sigmarszell","type":"Kreisangehörige_Gemeinde"},"district":{"key":"09776","name":"Lindau (Bodensee)","type":"Landkreis"},"federalState":{"key":"09","name":"Bayern"}},{"name":"Norbert-Jacques-Weg","postalCode":"88138","locality":"Sigmarszell","municipality":{"key":"09776126","name":"Sigmarszell","type":"Kreisangehörige_Gemeinde"},"district":{"key":"09776","name":"Lindau (Bodensee)","type":"Landkreis"},"federalState":{"key":"09","name":"Bayern"}},{"name":"Oeschweg","postalCode":"88138","locality":"Sigmarszell","municipality":{"key":"09776126","name":"Sigmarszell","type":"Kreisangehörige_Gemeinde"},"district":{"key":"09776","name":"Lindau (Bodensee)","type":"Landkreis"},"federalState":{"key":"09","name":"Bayern"}},{"name":"Pfänderblick","postalCode":"88138","locality":"Sigmarszell","municipality":{"key":"09776126","name":"Sigmarszell","type":"Kreisangehörige_Gemeinde"},"district":{"key":"09776","name":"Lindau (Bodensee)","type":"Landkreis"},"federalState":{"key":"09","name":"Bayern"}},{"name":"Pfarrer-Wolfgruber-Str.","postalCode":"88138","locality":"Sigmarszell","municipality":{"key":"09776126","name":"Sigmarszell","type":"Kreisangehörige_Gemeinde"},"district":{"key":"09776","name":"Lindau (Bodensee)","type":"Landkreis"},"federalState":{"key":"09","name":"Bayern"}},{"name":"Ringstr.","postalCode":"88138","locality":"Sigmarszell","municipality":{"key":"09776126","name":"Sigmarszell","type":"Kreisangehörige_Gemeinde"},"district":{"key":"09776","name":"Lindau (Bodensee)","type":"Landkreis"},"federalState":{"key":"09","name":"Bayern"}},{"name":"Sonnenhalde","postalCode":"88138","locality":"Sigmarszell","municipality":{"key":"09776126","name":"Sigmarszell","type":"Kreisangehörige_Gemeinde"},"district":{"key":"09776","name":"Lindau (Bodensee)","type":"Landkreis"},"federalState":{"key":"09","name":"Bayern"}},{"name":"Sulzerwiese","postalCode":"88138","locality":"Sigmarszell","municipality":{"key":"09776126","name":"Sigmarszell","type":"Kreisangehörige_Gemeinde"},"district":{"key":"09776","name":"Lindau (Bodensee)","type":"Landkreis"},"federalState":{"key":"09","name":"Bayern"}},{"name":"Waldbergweg","postalCode":"88138","locality":"Sigmarszell","municipality":{"key":"09776126","name":"Sigmarszell","type":"Kreisangehörige_Gemeinde"},"district":{"key":"09776","name":"Lindau (Bodensee)","type":"Landkreis"},"federalState":{"key":"09","name":"Bayern"}},{"name":"Widdum","postalCode":"88138","locality":"Sigmarszell","municipality":{"key":"09776126","name":"Sigmarszell","type":"Kreisangehörige_Gemeinde"},"district":{"key":"09776","name":"Lindau (Bodensee)","type":"Landkreis"},"federalState":{"key":"09","name":"Bayern"}},{"name":"Wiesenstr.","postalCode":"88138","locality":"Sigmarszell","municipality":{"key":"09776126","name":"Sigmarszell","type":"Kreisangehörige_Gemeinde"},"district":{"key":"09776","name":"Lindau (Bodensee)","type":"Landkreis"},"federalState":{"key":"09","name":"Bayern"}},{"name":"Zeisertsweiler","postalCode":"88138","locality":"Sigmarszell","municipality":{"key":"09776126","name":"Sigmarszell","type":"Kreisangehörige_Gemeinde"},"district":{"key":"09776","name":"Lindau (Bodensee)","type":"Landkreis"},"federalState":{"key":"09","name":"Bayern"}},{"name":"Zellersteg","postalCode":"88138","locality":"Sigmarszell","municipality":{"key":"09776126","name":"Sigmarszell","type":"Kreisangehörige_Gemeinde"},"district":{"key":"09776","name":"Lindau (Bodensee)","type":"Landkreis"},"federalState":{"key":"09","name":"Bayern"}},{"name":"Zeller Str.","postalCode":"88138","locality":"Sigmarszell","municipality":{"key":"09776126","name":"Sigmarszell","type":"Kreisangehörige_Gemeinde"},"district":{"key":"09776","name":"Lindau (Bodensee)","type":"Landkreis"},"federalState":{"key":"09","name":"Bayern"}},]