[{"name":"Am Berg","postalCode":"54552","locality":"Sarmersbach","municipality":{"key":"07233061","name":"Sarmersbach","type":"Kreisangehörige_Gemeinde"},"district":{"key":"07233","name":"Vulkaneifel","type":"Landkreis"},"federalState":{"key":"07","name":"Rheinland-Pfalz"}},{"name":"Bergstr.","postalCode":"54552","locality":"Sarmersbach","municipality":{"key":"07233061","name":"Sarmersbach","type":"Kreisangehörige_Gemeinde"},"district":{"key":"07233","name":"Vulkaneifel","type":"Landkreis"},"federalState":{"key":"07","name":"Rheinland-Pfalz"}},{"name":"Darscheider Weg","postalCode":"54552","locality":"Sarmersbach","municipality":{"key":"07233061","name":"Sarmersbach","type":"Kreisangehörige_Gemeinde"},"district":{"key":"07233","name":"Vulkaneifel","type":"Landkreis"},"federalState":{"key":"07","name":"Rheinland-Pfalz"}},{"name":"Gefeller Weg","postalCode":"54552","locality":"Sarmersbach","municipality":{"key":"07233061","name":"Sarmersbach","type":"Kreisangehörige_Gemeinde"},"district":{"key":"07233","name":"Vulkaneifel","type":"Landkreis"},"federalState":{"key":"07","name":"Rheinland-Pfalz"}},{"name":"Hauptstr.","postalCode":"54552","locality":"Sarmersbach","municipality":{"key":"07233061","name":"Sarmersbach","type":"Kreisangehörige_Gemeinde"},"district":{"key":"07233","name":"Vulkaneifel","type":"Landkreis"},"federalState":{"key":"07","name":"Rheinland-Pfalz"}},{"name":"Hilgerather Str.","postalCode":"54552","locality":"Sarmersbach","municipality":{"key":"07233061","name":"Sarmersbach","type":"Kreisangehörige_Gemeinde"},"district":{"key":"07233","name":"Vulkaneifel","type":"Landkreis"},"federalState":{"key":"07","name":"Rheinland-Pfalz"}},{"name":"Jagdhütte","postalCode":"54552","locality":"Sarmersbach","municipality":{"key":"07233061","name":"Sarmersbach","type":"Kreisangehörige_Gemeinde"},"district":{"key":"07233","name":"Vulkaneifel","type":"Landkreis"},"federalState":{"key":"07","name":"Rheinland-Pfalz"}},{"name":"Rundweg","postalCode":"54552","locality":"Sarmersbach","municipality":{"key":"07233061","name":"Sarmersbach","type":"Kreisangehörige_Gemeinde"},"district":{"key":"07233","name":"Vulkaneifel","type":"Landkreis"},"federalState":{"key":"07","name":"Rheinland-Pfalz"}},{"name":"Strümpelsweg","postalCode":"54552","locality":"Sarmersbach","municipality":{"key":"07233061","name":"Sarmersbach","type":"Kreisangehörige_Gemeinde"},"district":{"key":"07233","name":"Vulkaneifel","type":"Landkreis"},"federalState":{"key":"07","name":"Rheinland-Pfalz"}},]